Workbook
Name Accruals: Accruals!$A$1:$L$13
Name AccrualsMonthly: Accruals!$G$14
Name AccruedTotal: Accruals!$F$14
Name Categories: Expenses!$C:$C
Name CurrentMonth: Budget!$A$2
Name CurrentYear: Budget!$B$2
Name Deductions: Income!$I:$I
Name ExpenseAccounts: Expenses!$E:$E
Name ExpenseBudgets: Expenses!$B:$B
Name Expenses: Expenses!$A:$A
Name Gross: Income!$D:$D
Name Monthly: Income!$J:$J
Name MonthlyLeftover: 'Monthly Overview'!$B$12
Name Requiredness: Expenses!$D:$D
Name Source: Income!$B:$B
Name TotalAccrued: Accruals!$F$14
Name TotalMonthlyExpenses: ExpenseData[[#Totals],[Budget]]
Name TotalMonthlyExpenses: ExpenseData[[#Totals],[Budget]]
Name TotalMonthlyIncome: IncomeData[[#Totals],[Monthly]]
Name TotalMonthlyIncome: IncomeData[[#Totals],[Monthly]]
Name TotalSalary: IncomeData[[#Totals],[Salary]]
Name TotalSalary: IncomeData[[#Totals],[Salary]]
Name TransactionDates: Transactions[Date]
Name TransactionExpenseType: Transactions[Expense Type]
Name TransactionIds: Transactions[ID]
Name TransactionsAmount: Transactions[Amount]
Name Yearly: Income!$K:$K

Sheet Yearly Overview
B2: Total Expenses | D2: Budget Per Category
D3: Home | E3: Vehicle | F3: Travel | G3: Accruals | H3: Investments | I3: Food | J3: Shopping | K3: Leisure | L3: Personal | M3: Other
B4: {=TotalMonthlyExpenses*12} -> 89170.591 | D4: =SUMIF(Categories,D3,ExpenseBudgets)*12 -> 23701.02 | E4: =SUMIF(Categories,E3,ExpenseBudgets)*12 -> 8658 | F4: =SUMIF(Categories,F3,ExpenseBudgets)*12 -> 4080 | G4: =SUMIF(Categories,G3,ExpenseBudgets)*12 -> 9568.1307 | H4: =SUMIF(Categories,H3,ExpenseBudgets)*12 -> 6717.28 | I4: =SUMIF(Categories,I3,ExpenseBudgets)*12 -> 8400 | J4: =SUMIF(Categories,J3,ExpenseBudgets)*12 -> 12360 | K4: =SUMIF(Categories,K3,ExpenseBudgets)*12 -> 6283.92 | ... M4: =SUMIF(Categories,M3,ExpenseBudgets)*12 -> 120
B6: Total Income | E6: Need | F6: Want | G6: Total
D7: Chequing | E7: =SUMIFS(ExpenseBudgets,Requiredness,E6,ExpenseAccounts,D7)*12 -> 39079.02 | F7: =SUMIFS(ExpenseBudgets,Requiredness,F6,ExpenseAccounts,D7)*12 -> 8486.16 | G7: =SUMIF(ExpenseAccounts,D7,ExpenseBudgets)*12 -> 54282.46
B8: {=TotalMonthlyIncome*12} -> 96410.34 | D8: Saving | E8: =SUMIFS(ExpenseBudgets,Requiredness,E6,ExpenseAccounts,D8)*12 -> 2400 | F8: =SUMIFS(ExpenseBudgets,Requiredness,F6,ExpenseAccounts,D8)*12 -> 22888.131 | G8: =SUMIF(ExpenseAccounts,D8,ExpenseBudgets)*12 -> 34888.131
D9: Total | E9: =SUMIF(Requiredness,E6,ExpenseBudgets)*12 -> 41479.02 | F9: =SUMIF(Requiredness,F6,ExpenseBudgets)*12 -> 31374.291
B10: Balance
B12: {=(TotalMonthlyIncome-TotalMonthlyExpenses)*12} -> 7239.7493

Sheet Monthly Overview
B2: Total Expenses | D2: Budgeted Per Category
D3: Home | E3: Vehicle | F3: Travel | G3: Accruals | H3: Investments | I3: Food | J3: Shopping | K3: Leisure | L3: Personal | M3: Other
B4: {=TotalMonthlyExpenses} -> 7430.8826 | D4: =SUMIF(Categories,D3,ExpenseBudgets) -> 1975.085 | E4: =SUMIF(Categories,E3,ExpenseBudgets) -> 721.5 | F4: =SUMIF(Categories,F3,ExpenseBudgets) -> 340 | G4: =SUMIF(Categories,G3,ExpenseBudgets) -> 797.34423 | H4: =SUMIF(Categories,H3,ExpenseBudgets) -> 559.77333 | I4: =SUMIF(Categories,I3,ExpenseBudgets) -> 700 | J4: =SUMIF(Categories,J3,ExpenseBudgets) -> 1030 | K4: =SUMIF(Categories,K3,ExpenseBudgets) -> 523.66 | ... M4: =SUMIF(Categories,M3,ExpenseBudgets) -> 10
B6: Total Income
E7: Need | F7: Smart | G7: Want | H7: Total
B8: {=TotalMonthlyIncome} -> 8034.195 | D8: Chequing | E8: =SUMIFS(ExpenseBudgets,Requiredness,E7,ExpenseAccounts,D8) -> 3256.585 | F8: =SUMIFS(ExpenseBudgets,Requiredness,F7,ExpenseAccounts,D8) -> 559.77333 | G8: =SUMIFS(ExpenseBudgets,Requiredness,G7,ExpenseAccounts,D8) -> 707.18 | H8: =SUMIF(ExpenseAccounts,D8,ExpenseBudgets) -> 4523.5383
D9: Saving | E9: =SUMIFS(ExpenseBudgets,Requiredness,E7,ExpenseAccounts,D9) -> 200 | F9: =SUMIFS(ExpenseBudgets,Requiredness,F7,ExpenseAccounts,D9) -> 800 | G9: =SUMIFS(ExpenseBudgets,Requiredness,G7,ExpenseAccounts,D9) -> 1907.3442 | H9: =SUMIF(ExpenseAccounts,D9,ExpenseBudgets) -> 2907.3442
B10: Balance | D10: Total | E10: =SUMIF(Requiredness,E7,ExpenseBudgets) -> 3456.585 | F10: =SUMIF(Requiredness,F7,ExpenseBudgets) -> 1359.7733 | G10: =SUMIF(Requiredness,G7,ExpenseBudgets) -> 2614.5242
B12: {=TotalMonthlyIncome-TotalMonthlyExpenses} -> 603.31244 | G12: =E10+F10 -> 4816.3583

Sheet Budget
A1: Month | B1: Year | D1: Chequings | J1: Chequings | P1: Savings
A2: 2 | B2: 2025 | D2: Rollover | E2: Budgeted | F2: Spent | G2: Remaining | J2: Rollover | K2: Budgeted | L2: Spent | M2: Remaining | P2: Rollover | Q2: Budgeted | R2: Spent | S2: Remaining
C3: Auto Insurance | D3: {=INDEX(Rollovers[BOM], MATCH(1, (Rollovers[Month]=CurrentMonth)*(Rollovers[Year]=CurrentYear)*(Rollovers[Expense]=C3), 0))} -> 2.5 | E3: =_xlfn.LET( _xlpm.CurrDate, DATE(CurrentYear,CurrentMonth,1), _xlpm.Result, SUMIFS( BudgetHistory[Amount], BudgetHistory[Expense], C3, BudgetHistory[StartDate], "<=" & _xlpm.CurrDate, BudgetHistory[EndDate], ">=" & _xlpm.CurrDate ), IF(_xlpm.Result = 0, INDEX(ExpenseBudgets, MATCH(C3, Expenses!$A:$A, 0)), _xlpm.Result) ) -> 226 | F3: {=SUMIFS(TransactionsAmount, TransactionExpenseType, C3, TransactionDates, ">=" & DATE(CurrentYear, CurrentMonth, 1), TransactionDates, "<" & DATE(CurrentYear + IF(CurrentMonth=12, 1, 0), MOD(CurrentMonth, 12) + 1, 1))} -> 0 | G3: =D3+E3+F3 -> 228.5 | I3: Home Insurance | J3: {=INDEX(Rollovers[BOM], MATCH(1, (Rollovers[Month]=CurrentMonth)*(Rollovers[Year]=CurrentYear)*(Rollovers[Expense]=I3), 0))} -> 0.09 | K3: =_xlfn.LET( _xlpm.CurrDate, DATE(CurrentYear,CurrentMonth,1), _xlpm.Result, SUMIFS( BudgetHistory[Amount], BudgetHistory[Expense], I3, BudgetHistory[StartDate], "<=" & _xlpm.CurrDate, BudgetHistory[EndDate], ">=" & _xlpm.CurrDate ), IF(_xlpm.Result = 0, INDEX(ExpenseBudgets, MATCH(I3, Expenses!$A:$A, 0)), _xlpm.Result) ) -> 214.82 | L3: {=SUMIFS(TransactionsAmount, TransactionExpenseType, I3, TransactionDates, ">=" & DATE(CurrentYear, CurrentMonth, 1), TransactionDates, "<" & DATE(CurrentYear + IF(CurrentMonth=12, 1, 0), MOD(CurrentMonth, 12) + 1, 1))} -> -214.82 | M3: =J3+K3+L3 -> 0.09 | O3: Vacation Fund | P3: {=INDEX(Rollovers[BOM], MATCH(1, (Rollovers[Month]=CurrentMonth)*(Rollovers[Year]=CurrentYear)*(Rollovers[Expense]=O3), 0))} -> 865.98 | Q3: =_xlfn.LET( _xlpm.CurrDate, DATE(CurrentYear,CurrentMonth,1), _xlpm.Result, SUMIFS( BudgetHistory[Amount], BudgetHistory[Expense], O3, BudgetHistory[StartDate], "<=" & _xlpm.CurrDate, BudgetHistory[EndDate], ">=" & _xlpm.CurrDate ), IF(_xlpm.Result = 0, INDEX(ExpenseBudgets, MATCH(O3, Expenses!$A:$A, 0)), _xlpm.Result) ) -> 200 | R3: {=SUMIFS(TransactionsAmount, TransactionExpenseType, O3, TransactionDates, ">=" & DATE(CurrentYear, CurrentMonth, 1), TransactionDates, "<" & DATE(CurrentYear + IF(CurrentMonth=12, 1, 0), MOD(CurrentMonth, 12) + 1, 1))} -> 0 | S3: =P3+Q3+R3 -> 1065.98
C4: Car Fuel | D4: {=INDEX(Rollovers[BOM], MATCH(1, (Rollovers[Month]=CurrentMonth)*(Rollovers[Year]=CurrentYear)*(Rollovers[Expense]=C4), 0))} -> -381.07 | E4: =_xlfn.LET( _xlpm.CurrDate, DATE(CurrentYear,CurrentMonth,1), _xlpm.Result, SUMIFS( BudgetHistory[Amount], BudgetHistory[Expense], C4, BudgetHistory[StartDate], "<=" & _xlpm.CurrDate, BudgetHistory[EndDate], ">=" & _xlpm.CurrDate ), IF(_xlpm.Result = 0, INDEX(ExpenseBudgets, MATCH(C4, Expenses!$A:$A, 0)), _xlpm.Result) ) -> 300 | F4: {=SUMIFS(TransactionsAmount, TransactionExpenseType, C4, TransactionDates, ">=" & DATE(CurrentYear, CurrentMonth, 1), TransactionDates, "<" & DATE(CurrentYear + IF(CurrentMonth=12, 1, 0), MOD(CurrentMonth, 12) + 1, 1))} -> -86.72 | G4: =D4+E4+F4 -> -167.79 | I4: Mortgage | J4: {=INDEX(Rollovers[BOM], MATCH(1, (Rollovers[Month]=CurrentMonth)*(Rollovers[Year]=CurrentYear)*(Rollovers[Expense]=I4), 0))} -> 75.16 | K4: =_xlfn.LET( _xlpm.CurrDate, DATE(CurrentYear,CurrentMonth,1), _xlpm.Result, SUMIFS( BudgetHistory[Amount], BudgetHistory[Expense], I4, BudgetHistory[StartDate], "<=" & _xlpm.CurrDate, BudgetHistory[EndDate], ">=" & _xlpm.CurrDate ), IF(_xlpm.Result = 0, INDEX(ExpenseBudgets, MATCH(I4, Expenses!$A:$A, 0)), _xlpm.Result) ) -> 960.375 | L4: {=SUMIFS(TransactionsAmount, TransactionExpenseType, I4, TransactionDates, ">=" & DATE(CurrentYear, CurrentMonth, 1), TransactionDates, "<" & DATE(CurrentYear + IF(CurrentMonth=12, 1, 0), MOD(CurrentMonth, 12) + 1, 1))} -> -886.5 | M4: =J4+K4+L4 -> 149.035 | O4: Weekend Trips | P4: {=INDEX(Rollovers[BOM], MATCH(1, (Rollovers[Month]=CurrentMonth)*(Rollovers[Year]=CurrentYear)*(Rollovers[Expense]=O4), 0))} -> -27.91 | Q4: =_xlfn.LET( _xlpm.CurrDate, DATE(CurrentYear,CurrentMonth,1), _xlpm.Result, SUMIFS( BudgetHistory[Amount], BudgetHistory[Expense], O4, BudgetHistory[StartDate], "<=" & _xlpm.CurrDate, BudgetHistory[EndDate], ">=" & _xlpm.CurrDate ), IF(_xlpm.Result = 0, INDEX(ExpenseBudgets, MATCH(O4, Expenses!$A:$A, 0)), _xlpm.Result) ) -> 140 | R4: {=SUMIFS(TransactionsAmount, TransactionExpenseType, O4, TransactionDates, ">=" & DATE(CurrentYear, CurrentMonth, 1), TransactionDates, "<" & DATE(CurrentYear + IF(CurrentMonth=12, 1, 0), MOD(CurrentMonth, 12) + 1, 1))} -> -71.15 | S4: =P4+Q4+R4 -> 40.94
C5: Internet Bill | D5: {=INDEX(Rollovers[BOM], MATCH(1, (Rollovers[Month]=CurrentMonth)*(Rollovers[Year]=CurrentYear)*(Rollovers[Expense]=C5), 0))} -> 0 | E5: =_xlfn.LET( _xlpm.CurrDate, DATE(CurrentYear,CurrentMonth,1), _xlpm.Result, SUMIFS( BudgetHistory[Amount], BudgetHistory[Expense], C5, BudgetHistory[StartDate], "<=" & _xlpm.CurrDate, BudgetHistory[EndDate], ">=" & _xlpm.CurrDate ), IF(_xlpm.Result = 0, INDEX(ExpenseBudgets, MATCH(C5, Expenses!$A:$A, 0)), _xlpm.Result) ) -> 88.14 | F5: {=SUMIFS(TransactionsAmount, TransactionExpenseType, C5, TransactionDates, ">=" & DATE(CurrentYear, CurrentMonth, 1), TransactionDates, "<" & DATE(CurrentYear + IF(CurrentMonth=12, 1, 0), MOD(CurrentMonth, 12) + 1, 1))} -> -88.14 | G5: =D5+E5+F5 -> 0 | I5: Sewer/Water | J5: {=INDEX(Rollovers[BOM], MATCH(1, (Rollovers[Month]=CurrentMonth)*(Rollovers[Year]=CurrentYear)*(Rollovers[Expense]=I5), 0))} -> 53.12 | K5: =_xlfn.LET( _xlpm.CurrDate, DATE(CurrentYear,CurrentMonth,1), _xlpm.Result, SUMIFS( BudgetHistory[Amount], BudgetHistory[Expense], I5, BudgetHistory[StartDate], "<=" & _xlpm.CurrDate, BudgetHistory[EndDate], ">=" & _xlpm.CurrDate ), IF(_xlpm.Result = 0, INDEX(ExpenseBudgets, MATCH(I5, Expenses!$A:$A, 0)), _xlpm.Result) ) -> 85 | L5: {=SUMIFS(TransactionsAmount, TransactionExpenseType, I5, TransactionDates, ">=" & DATE(CurrentYear, CurrentMonth, 1), TransactionDates, "<" & DATE(CurrentYear + IF(CurrentMonth=12, 1, 0), MOD(CurrentMonth, 12) + 1, 1))} -> -66.64 | M5: =J5+K5+L5 -> 71.48 | O5: Electronics Fund | P5: {=INDEX(Rollovers[BOM], MATCH(1, (Rollovers[Month]=CurrentMonth)*(Rollovers[Year]=CurrentYear)*(Rollovers[Expense]=O5), 0))} -> -290.42 | Q5: =_xlfn.LET( _xlpm.CurrDate, DATE(CurrentYear,CurrentMonth,1), _xlpm.Result, SUMIFS( BudgetHistory[Amount], BudgetHistory[Expense], O5, BudgetHistory[StartDate], "<=" & _xlpm.CurrDate, BudgetHistory[EndDate], ">=" & _xlpm.CurrDate ), IF(_xlpm.Result = 0, INDEX(ExpenseBudgets, MATCH(O5, Expenses!$A:$A, 0)), _xlpm.Result) ) -> 150 | R5: {=SUMIFS(TransactionsAmount, TransactionExpenseType, O5, TransactionDates, ">=" & DATE(CurrentYear, CurrentMonth, 1), TransactionDates, "<" & DATE(CurrentYear + IF(CurrentMonth=12, 1, 0), MOD(CurrentMonth, 12) + 1, 1))} -> 0 | S5: =P5+Q5+R5 -> -140.42 | T5: ?
C6: Phone Bills | D6: {=INDEX(Rollovers[BOM], MATCH(1, (Rollovers[Month]=CurrentMonth)*(Rollovers[Year]=CurrentYear)*(Rollovers[Expense]=C6), 0))} -> -15.48 | E6: =_xlfn.LET( _xlpm.CurrDate, DATE(CurrentYear,CurrentMonth,1), _xlpm.Result, SUMIFS( BudgetHistory[Amount], BudgetHistory[Expense], C6, BudgetHistory[StartDate], "<=" & _xlpm.CurrDate, BudgetHistory[EndDate], ">=" & _xlpm.CurrDate ), IF(_xlpm.Result = 0, INDEX(ExpenseBudgets, MATCH(C6, Expenses!$A:$A, 0)), _xlpm.Result) ) -> 104.62 | F6: {=SUMIFS(TransactionsAmount, TransactionExpenseType, C6, TransactionDates, ">=" & DATE(CurrentYear, CurrentMonth, 1), TransactionDates, "<" & DATE(CurrentYear + IF(CurrentMonth=12, 1, 0), MOD(CurrentMonth, 12) + 1, 1))} -> -125.43 | G6: =D6+E6+F6 -> -36.29 | I6: Allowances | J6: {=INDEX(Rollovers[BOM], MATCH(1, (Rollovers[Month]=CurrentMonth)*(Rollovers[Year]=CurrentYear)*(Rollovers[Expense]=I6), 0))} -> 0 | K6: =_xlfn.LET( _xlpm.CurrDate, DATE(CurrentYear,CurrentMonth,1), _xlpm.Result, SUMIFS( BudgetHistory[Amount], BudgetHistory[Expense], I6, BudgetHistory[StartDate], "<=" & _xlpm.CurrDate, BudgetHistory[EndDate], ">=" & _xlpm.CurrDate ), IF(_xlpm.Result = 0, INDEX(ExpenseBudgets, MATCH(I6, Expenses!$A:$A, 0)), _xlpm.Result) ) -> 400 | L6: {=SUMIFS(TransactionsAmount, TransactionExpenseType, I6, TransactionDates, ">=" & DATE(CurrentYear, CurrentMonth, 1), TransactionDates, "<" & DATE(CurrentYear + IF(CurrentMonth=12, 1, 0), MOD(CurrentMonth, 12) + 1, 1))} -> -400 | M6: =J6+K6+L6 -> 0 | O6: Date Night | P6: {=INDEX(Rollovers[BOM], MATCH(1, (Rollovers[Month]=CurrentMonth)*(Rollovers[Year]=CurrentYear)*(Rollovers[Expense]=O6), 0))} -> 75.44 | Q6: =_xlfn.LET( _xlpm.CurrDate, DATE(CurrentYear,CurrentMonth,1), _xlpm.Result, SUMIFS( BudgetHistory[Amount], BudgetHistory[Expense], O6, BudgetHistory[StartDate], "<=" & _xlpm.CurrDate, BudgetHistory[EndDate], ">=" & _xlpm.CurrDate ), IF(_xlpm.Result = 0, INDEX(ExpenseBudgets, MATCH(O6, Expenses!$A:$A, 0)), _xlpm.Result) ) -> 50 | R6: {=SUMIFS(TransactionsAmount, TransactionExpenseType, O6, TransactionDates, ">=" & DATE(CurrentYear, CurrentMonth, 1), TransactionDates, "<" & DATE(CurrentYear + IF(CurrentMonth=12, 1, 0), MOD(CurrentMonth, 12) + 1, 1))} -> -107.26 | S6: =P6+Q6+R6 -> 18.18
C7: Subscriptions | D7: {=INDEX(Rollovers[BOM], MATCH(1, (Rollovers[Month]=CurrentMonth)*(Rollovers[Year]=CurrentYear)*(Rollovers[Expense]=C7), 0))} -> 232.74 | E7: =_xlfn.LET( _xlpm.CurrDate, DATE(CurrentYear,CurrentMonth,1), _xlpm.Result, SUMIFS( BudgetHistory[Amount], BudgetHistory[Expense], C7, BudgetHistory[StartDate], "<=" & _xlpm.CurrDate, BudgetHistory[EndDate], ">=" & _xlpm.CurrDate ), IF(_xlpm.Result = 0, INDEX(ExpenseBudgets, MATCH(C7, Expenses!$A:$A, 0)), _xlpm.Result) ) -> 8.66 | F7: {=SUMIFS(TransactionsAmount, TransactionExpenseType, C7, TransactionDates, ">=" & DATE(CurrentYear, CurrentMonth, 1), TransactionDates, "<" & DATE(CurrentYear + IF(CurrentMonth=12, 1, 0), MOD(CurrentMonth, 12) + 1, 1))} -> -25.98 | G7: =D7+E7+F7 -> 215.42 | I7: Gym | J7: {=INDEX(Rollovers[BOM], MATCH(1, (Rollovers[Month]=CurrentMonth)*(Rollovers[Year]=CurrentYear)*(Rollovers[Expense]=I7), 0))} -> -25.26 | K7: =_xlfn.LET( _xlpm.CurrDate, DATE(CurrentYear,CurrentMonth,1), _xlpm.Result, SUMIFS( BudgetHistory[Amount], BudgetHistory[Expense], I7, BudgetHistory[StartDate], "<=" & _xlpm.CurrDate, BudgetHistory[EndDate], ">=" & _xlpm.CurrDate ), IF(_xlpm.Result = 0, INDEX(ExpenseBudgets, MATCH(I7, Expenses!$A:$A, 0)), _xlpm.Result) ) -> 49.295 | L7: {=SUMIFS(TransactionsAmount, TransactionExpenseType, I7, TransactionDates, ">=" & DATE(CurrentYear, CurrentMonth, 1), TransactionDates, "<" & DATE(CurrentYear + IF(CurrentMonth=12, 1, 0), MOD(CurrentMonth, 12) + 1, 1))} -> -18.06 | M7: =J7+K7+L7 -> 5.975 | O7: Clothes | P7: {=INDEX(Rollovers[BOM], MATCH(1, (Rollovers[Month]=CurrentMonth)*(Rollovers[Year]=CurrentYear)*(Rollovers[Expense]=O7), 0))} -> 477.04 | Q7: =_xlfn.LET( _xlpm.CurrDate, DATE(CurrentYear,CurrentMonth,1), _xlpm.Result, SUMIFS( BudgetHistory[Amount], BudgetHistory[Expense], O7, BudgetHistory[StartDate], "<=" & _xlpm.CurrDate, BudgetHistory[EndDate], ">=" & _xlpm.CurrDate ), IF(_xlpm.Result = 0, INDEX(ExpenseBudgets, MATCH(O7, Expenses!$A:$A, 0)), _xlpm.Result) ) -> 140 | R7: {=SUMIFS(TransactionsAmount, TransactionExpenseType, O7, TransactionDates, ">=" & DATE(CurrentYear, CurrentMonth, 1), TransactionDates, "<" & DATE(CurrentYear + IF(CurrentMonth=12, 1, 0), MOD(CurrentMonth, 12) + 1, 1))} -> -67.73 | S7: =P7+Q7+R7 -> 549.31
C8: Weed | D8: {=INDEX(Rollovers[BOM], MATCH(1, (Rollovers[Month]=CurrentMonth)*(Rollovers[Year]=CurrentYear)*(Rollovers[Expense]=C8), 0))} -> 17.08 | E8: =_xlfn.LET( _xlpm.CurrDate, DATE(CurrentYear,CurrentMonth,1), _xlpm.Result, SUMIFS( BudgetHistory[Amount], BudgetHistory[Expense], C8, BudgetHistory[StartDate], "<=" & _xlpm.CurrDate, BudgetHistory[EndDate], ">=" & _xlpm.CurrDate ), IF(_xlpm.Result = 0, INDEX(ExpenseBudgets, MATCH(C8, Expenses!$A:$A, 0)), _xlpm.Result) ) -> 65 | F8: {=SUMIFS(TransactionsAmount, TransactionExpenseType, C8, TransactionDates, ">=" & DATE(CurrentYear, CurrentMonth, 1), TransactionDates, "<" & DATE(CurrentYear + IF(CurrentMonth=12, 1, 0), MOD(CurrentMonth, 12) + 1, 1))} -> -33.89 | G8: =D8+E8+F8 -> 48.19 | I8: Lottery | J8: {=INDEX(Rollovers[BOM], MATCH(1, (Rollovers[Month]=CurrentMonth)*(Rollovers[Year]=CurrentYear)*(Rollovers[Expense]=I8), 0))} -> 0 | K8: =_xlfn.LET( _xlpm.CurrDate, DATE(CurrentYear,CurrentMonth,1), _xlpm.Result, SUMIFS( BudgetHistory[Amount], BudgetHistory[Expense], I8, BudgetHistory[StartDate], "<=" & _xlpm.CurrDate, BudgetHistory[EndDate], ">=" & _xlpm.CurrDate ), IF(_xlpm.Result = 0, INDEX(ExpenseBudgets, MATCH(I8, Expenses!$A:$A, 0)), _xlpm.Result) ) -> 20 | L8: {=SUMIFS(TransactionsAmount, TransactionExpenseType, I8, TransactionDates, ">=" & DATE(CurrentYear, CurrentMonth, 1), TransactionDates, "<" & DATE(CurrentYear + IF(CurrentMonth=12, 1, 0), MOD(CurrentMonth, 12) + 1, 1))} -> -20 | M8: =J8+K8+L8 -> 0 | O8: Gifts | P8: {=INDEX(Rollovers[BOM], MATCH(1, (Rollovers[Month]=CurrentMonth)*(Rollovers[Year]=CurrentYear)*(Rollovers[Expense]=O8), 0))} -> -251.07 | Q8: =_xlfn.LET( _xlpm.CurrDate, DATE(CurrentYear,CurrentMonth,1), _xlpm.Result, SUMIFS( BudgetHistory[Amount], BudgetHistory[Expense], O8, BudgetHistory[StartDate], "<=" & _xlpm.CurrDate, BudgetHistory[EndDate], ">=" & _xlpm.CurrDate ), IF(_xlpm.Result = 0, INDEX(ExpenseBudgets, MATCH(O8, Expenses!$A:$A, 0)), _xlpm.Result) ) -> 200 | R8: {=SUMIFS(TransactionsAmount, TransactionExpenseType, O8, TransactionDates, ">=" & DATE(CurrentYear, CurrentMonth, 1), TransactionDates, "<" & DATE(CurrentYear + IF(CurrentMonth=12, 1, 0), MOD(CurrentMonth, 12) + 1, 1))} -> -84.16 | S8: =P8+Q8+R8 -> -135.23
C9: Misc Fees | D9: {=INDEX(Rollovers[BOM], MATCH(1, (Rollovers[Month]=CurrentMonth)*(Rollovers[Year]=CurrentYear)*(Rollovers[Expense]=C9), 0))} -> 24.81 | E9: =_xlfn.LET( _xlpm.CurrDate, DATE(CurrentYear,CurrentMonth,1), _xlpm.Result, SUMIFS( BudgetHistory[Amount], BudgetHistory[Expense], C9, BudgetHistory[StartDate], "<=" & _xlpm.CurrDate, BudgetHistory[EndDate], ">=" & _xlpm.CurrDate ), IF(_xlpm.Result = 0, INDEX(ExpenseBudgets, MATCH(C9, Expenses!$A:$A, 0)), _xlpm.Result) ) -> 10 | F9: {=SUMIFS(TransactionsAmount, TransactionExpenseType, C9, TransactionDates, ">=" & DATE(CurrentYear, CurrentMonth, 1), TransactionDates, "<" & DATE(CurrentYear + IF(CurrentMonth=12, 1, 0), MOD(CurrentMonth, 12) + 1, 1))} -> -8.9 | G9: =D9+E9+F9 -> 25.91 | I9: RRSP | J9: {=INDEX(Rollovers[BOM], MATCH(1, (Rollovers[Month]=CurrentMonth)*(Rollovers[Year]=CurrentYear)*(Rollovers[Expense]=I9), 0))} -> 0 | K9: =_xlfn.LET( _xlpm.CurrDate, DATE(CurrentYear,CurrentMonth,1), _xlpm.Result, SUMIFS( BudgetHistory[Amount], BudgetHistory[Expense], I9, BudgetHistory[StartDate], "<=" & _xlpm.CurrDate, BudgetHistory[EndDate], ">=" & _xlpm.CurrDate ), IF(_xlpm.Result = 0, INDEX(ExpenseBudgets, MATCH(I9, Expenses!$A:$A, 0)), _xlpm.Result) ) -> 150 | L9: {=SUMIFS(TransactionsAmount, TransactionExpenseType, I9, TransactionDates, ">=" & DATE(CurrentYear, CurrentMonth, 1), TransactionDates, "<" & DATE(CurrentYear + IF(CurrentMonth=12, 1, 0), MOD(CurrentMonth, 12) + 1, 1))} -> -150 | M9: =J9+K9+L9 -> 0 | O9: Alcohol | P9: {=INDEX(Rollovers[BOM], MATCH(1, (Rollovers[Month]=CurrentMonth)*(Rollovers[Year]=CurrentYear)*(Rollovers[Expense]=O9), 0))} -> 58.62 | Q9: =_xlfn.LET( _xlpm.CurrDate, DATE(CurrentYear,CurrentMonth,1), _xlpm.Result, SUMIFS( BudgetHistory[Amount], BudgetHistory[Expense], O9, BudgetHistory[StartDate], "<=" & _xlpm.CurrDate, BudgetHistory[EndDate], ">=" & _xlpm.CurrDate ), IF(_xlpm.Result = 0, INDEX(ExpenseBudgets, MATCH(O9, Expenses!$A:$A, 0)), _xlpm.Result) ) -> 130 | R9: {=SUMIFS(TransactionsAmount, TransactionExpenseType, O9, TransactionDates, ">=" & DATE(CurrentYear, CurrentMonth, 1), TransactionDates, "<" & DATE(CurrentYear + IF(CurrentMonth=12, 1, 0), MOD(CurrentMonth, 12) + 1, 1))} -> -283.1 | S9: =P9+Q9+R9 -> -94.48
C10: Private Insurances | D10: {=INDEX(Rollovers[BOM], MATCH(1, (Rollovers[Month]=CurrentMonth)*(Rollovers[Year]=CurrentYear)*(Rollovers[Expense]=C10), 0))} -> 0 | E10: =_xlfn.LET( _xlpm.CurrDate, DATE(CurrentYear,CurrentMonth,1), _xlpm.Result, SUMIFS( BudgetHistory[Amount], BudgetHistory[Expense], C10, BudgetHistory[StartDate], "<=" & _xlpm.CurrDate, BudgetHistory[EndDate], ">=" & _xlpm.CurrDate ), IF(_xlpm.Result = 0, INDEX(ExpenseBudgets, MATCH(C10, Expenses!$A:$A, 0)), _xlpm.Result) ) -> 251.44 | F10: {=SUMIFS(TransactionsAmount, TransactionExpenseType, C10, TransactionDates, ">=" & DATE(CurrentYear, CurrentMonth, 1), TransactionDates, "<" & DATE(CurrentYear + IF(CurrentMonth=12, 1, 0), MOD(CurrentMonth, 12) + 1, 1))} -> -251.44 | G10: =D10+E10+F10 -> 0 | I10: Personal Care | J10: {=INDEX(Rollovers[BOM], MATCH(1, (Rollovers[Month]=CurrentMonth)*(Rollovers[Year]=CurrentYear)*(Rollovers[Expense]=I10), 0))} -> -61.28 | K10: =_xlfn.LET( _xlpm.CurrDate, DATE(CurrentYear,CurrentMonth,1), _xlpm.Result, SUMIFS( BudgetHistory[Amount], BudgetHistory[Expense], I10, BudgetHistory[StartDate], "<=" & _xlpm.CurrDate, BudgetHistory[EndDate], ">=" & _xlpm.CurrDate ), IF(_xlpm.Result = 0, INDEX(ExpenseBudgets, MATCH(I10, Expenses!$A:$A, 0)), _xlpm.Result) ) -> 100 | L10: {=SUMIFS(TransactionsAmount, TransactionExpenseType, I10, TransactionDates, ">=" & DATE(CurrentYear, CurrentMonth, 1), TransactionDates, "<" & DATE(CurrentYear + IF(CurrentMonth=12, 1, 0), MOD(CurrentMonth, 12) + 1, 1))} -> -34.92 | M10: =J10+K10+L10 -> 3.8 | O10: RV Fund | P10: {=INDEX(Rollovers[BOM], MATCH(1, (Rollovers[Month]=CurrentMonth)*(Rollovers[Year]=CurrentYear)*(Rollovers[Expense]=O10), 0))} -> 592.88 | Q10: =_xlfn.LET( _xlpm.CurrDate, DATE(CurrentYear,CurrentMonth,1), _xlpm.Result, SUMIFS( BudgetHistory[Amount], BudgetHistory[Expense], O10, BudgetHistory[StartDate], "<=" & _xlpm.CurrDate, BudgetHistory[EndDate], ">=" & _xlpm.CurrDate ), IF(_xlpm.Result = 0, INDEX(ExpenseBudgets, MATCH(O10, Expenses!$A:$A, 0)), _xlpm.Result) ) -> 100 | R10: {=SUMIFS(TransactionsAmount, TransactionExpenseType, O10, TransactionDates, ">=" & DATE(CurrentYear, CurrentMonth, 1), TransactionDates, "<" & DATE(CurrentYear + IF(CurrentMonth=12, 1, 0), MOD(CurrentMonth, 12) + 1, 1))} -> 0 | S10: =P10+Q10+R10 -> 692.88
C11: Fast Food | D11: {=INDEX(Rollovers[BOM], MATCH(1, (Rollovers[Month]=CurrentMonth)*(Rollovers[Year]=CurrentYear)*(Rollovers[Expense]=C11), 0))} -> 50.35 | E11: =_xlfn.LET( _xlpm.CurrDate, DATE(CurrentYear,CurrentMonth,1), _xlpm.Result, SUMIFS( BudgetHistory[Amount], BudgetHistory[Expense], C11, BudgetHistory[StartDate], "<=" & _xlpm.CurrDate, BudgetHistory[EndDate], ">=" & _xlpm.CurrDate ), IF(_xlpm.Result = 0, INDEX(ExpenseBudgets, MATCH(C11, Expenses!$A:$A, 0)), _xlpm.Result) ) -> 50 | F11: {=SUMIFS(TransactionsAmount, TransactionExpenseType, C11, TransactionDates, ">=" & DATE(CurrentYear, CurrentMonth, 1), TransactionDates, "<" & DATE(CurrentYear + IF(CurrentMonth=12, 1, 0), MOD(CurrentMonth, 12) + 1, 1))} -> -90.76 | G11: =D11+E11+F11 -> 9.59 | I11: Cat Fund | J11: {=INDEX(Rollovers[BOM], MATCH(1, (Rollovers[Month]=CurrentMonth)*(Rollovers[Year]=CurrentYear)*(Rollovers[Expense]=I11), 0))} -> 365.93 | K11: =_xlfn.LET( _xlpm.CurrDate, DATE(CurrentYear,CurrentMonth,1), _xlpm.Result, SUMIFS( BudgetHistory[Amount], BudgetHistory[Expense], I11, BudgetHistory[StartDate], "<=" & _xlpm.CurrDate, BudgetHistory[EndDate], ">=" & _xlpm.CurrDate ), IF(_xlpm.Result = 0, INDEX(ExpenseBudgets, MATCH(I11, Expenses!$A:$A, 0)), _xlpm.Result) ) -> 150 | L11: {=SUMIFS(TransactionsAmount, TransactionExpenseType, I11, TransactionDates, ">=" & DATE(CurrentYear, CurrentMonth, 1), TransactionDates, "<" & DATE(CurrentYear + IF(CurrentMonth=12, 1, 0), MOD(CurrentMonth, 12) + 1, 1))} -> -326.61 | M11: =J11+K11+L11 -> 189.32 | O11: Car Maintenance | P11: {=INDEX(Rollovers[BOM], MATCH(1, (Rollovers[Month]=CurrentMonth)*(Rollovers[Year]=CurrentYear)*(Rollovers[Expense]=O11), 0))} -> 995.43 | Q11: =_xlfn.LET( _xlpm.CurrDate, DATE(CurrentYear,CurrentMonth,1), _xlpm.Result, SUMIFS( BudgetHistory[Amount], BudgetHistory[Expense], O11, BudgetHistory[StartDate], "<=" & _xlpm.CurrDate, BudgetHistory[EndDate], ">=" & _xlpm.CurrDate ), IF(_xlpm.Result = 0, INDEX(ExpenseBudgets, MATCH(O11, Expenses!$A:$A, 0)), _xlpm.Result) ) -> 100 | R11: {=SUMIFS(TransactionsAmount, TransactionExpenseType, O11, TransactionDates, ">=" & DATE(CurrentYear, CurrentMonth, 1), TransactionDates, "<" & DATE(CurrentYear + IF(CurrentMonth=12, 1, 0), MOD(CurrentMonth, 12) + 1, 1))} -> 0 | S11: =P11+Q11+R11 -> 1095.43
C12: Grocery | D12: {=INDEX(Rollovers[BOM], MATCH(1, (Rollovers[Month]=CurrentMonth)*(Rollovers[Year]=CurrentYear)*(Rollovers[Expense]=C12), 0))} -> 88.07 | E12: =_xlfn.LET( _xlpm.CurrDate, DATE(CurrentYear,CurrentMonth,1), _xlpm.Result, SUMIFS( BudgetHistory[Amount], BudgetHistory[Expense], C12, BudgetHistory[StartDate], "<=" & _xlpm.CurrDate, BudgetHistory[EndDate], ">=" & _xlpm.CurrDate ), IF(_xlpm.Result = 0, INDEX(ExpenseBudgets, MATCH(C12, Expenses!$A:$A, 0)), _xlpm.Result) ) -> 600 | F12: {=SUMIFS(TransactionsAmount, TransactionExpenseType, C12, TransactionDates, ">=" & DATE(CurrentYear, CurrentMonth, 1), TransactionDates, "<" & DATE(CurrentYear + IF(CurrentMonth=12, 1, 0), MOD(CurrentMonth, 12) + 1, 1))} -> -435.1 | G12: =D12+E12+F12 -> 252.97 | I12: Shopping Fund | J12: {=INDEX(Rollovers[BOM], MATCH(1, (Rollovers[Month]=CurrentMonth)*(Rollovers[Year]=CurrentYear)*(Rollovers[Expense]=I12), 0))} -> -116.79 | K12: =_xlfn.LET( _xlpm.CurrDate, DATE(CurrentYear,CurrentMonth,1), _xlpm.Result, SUMIFS( BudgetHistory[Amount], BudgetHistory[Expense], I12, BudgetHistory[StartDate], "<=" & _xlpm.CurrDate, BudgetHistory[EndDate], ">=" & _xlpm.CurrDate ), IF(_xlpm.Result = 0, INDEX(ExpenseBudgets, MATCH(I12, Expenses!$A:$A, 0)), _xlpm.Result) ) -> 140 | L12: {=SUMIFS(TransactionsAmount, TransactionExpenseType, I12, TransactionDates, ">=" & DATE(CurrentYear, CurrentMonth, 1), TransactionDates, "<" & DATE(CurrentYear + IF(CurrentMonth=12, 1, 0), MOD(CurrentMonth, 12) + 1, 1))} -> -114.58 | M12: =J12+K12+L12 -> -91.37 | O12: Entertainment | P12: {=INDEX(Rollovers[BOM], MATCH(1, (Rollovers[Month]=CurrentMonth)*(Rollovers[Year]=CurrentYear)*(Rollovers[Expense]=O12), 0))} -> -84.17 | Q12: =_xlfn.LET( _xlpm.CurrDate, DATE(CurrentYear,CurrentMonth,1), _xlpm.Result, SUMIFS( BudgetHistory[Amount], BudgetHistory[Expense], O12, BudgetHistory[StartDate], "<=" & _xlpm.CurrDate, BudgetHistory[EndDate], ">=" & _xlpm.CurrDate ), IF(_xlpm.Result = 0, INDEX(ExpenseBudgets, MATCH(O12, Expenses!$A:$A, 0)), _xlpm.Result) ) -> 150 | R12: {=SUMIFS(TransactionsAmount, TransactionExpenseType, O12, TransactionDates, ">=" & DATE(CurrentYear, CurrentMonth, 1), TransactionDates, "<" & DATE(CurrentYear + IF(CurrentMonth=12, 1, 0), MOD(CurrentMonth, 12) + 1, 1))} -> -16.66 | S12: =P12+Q12+R12 -> 49.17
C13: Heat/Gas | D13: {=INDEX(Rollovers[BOM], MATCH(1, (Rollovers[Month]=CurrentMonth)*(Rollovers[Year]=CurrentYear)*(Rollovers[Expense]=C13), 0))} -> 194.26 | E13: =_xlfn.LET( _xlpm.CurrDate, DATE(CurrentYear,CurrentMonth,1), _xlpm.Result, SUMIFS( BudgetHistory[Amount], BudgetHistory[Expense], C13, BudgetHistory[StartDate], "<=" & _xlpm.CurrDate, BudgetHistory[EndDate], ">=" & _xlpm.CurrDate ), IF(_xlpm.Result = 0, INDEX(ExpenseBudgets, MATCH(C13, Expenses!$A:$A, 0)), _xlpm.Result) ) -> 101 | F13: {=SUMIFS(TransactionsAmount, TransactionExpenseType, C13, TransactionDates, ">=" & DATE(CurrentYear, CurrentMonth, 1), TransactionDates, "<" & DATE(CurrentYear + IF(CurrentMonth=12, 1, 0), MOD(CurrentMonth, 12) + 1, 1))} -> -87 | G13: =D13+E13+F13 -> 208.26 | I13: Business Line | J13: {=INDEX(Rollovers[BOM], MATCH(1, (Rollovers[Month]=CurrentMonth)*(Rollovers[Year]=CurrentYear)*(Rollovers[Expense]=I13), 0))} -> 150.011 | K13: =_xlfn.LET( _xlpm.CurrDate, DATE(CurrentYear,CurrentMonth,1), _xlpm.Result, SUMIFS( BudgetHistory[Amount], BudgetHistory[Expense], I13, BudgetHistory[StartDate], "<=" & _xlpm.CurrDate, BudgetHistory[EndDate], ">=" & _xlpm.CurrDate ), IF(_xlpm.Result = 0, INDEX(ExpenseBudgets, MATCH(I13, Expenses!$A:$A, 0)), _xlpm.Result) ) -> 150 | L13: {=SUMIFS(TransactionsAmount, TransactionExpenseType, I13, TransactionDates, ">=" & DATE(CurrentYear, CurrentMonth, 1), TransactionDates, "<" & DATE(CurrentYear + IF(CurrentMonth=12, 1, 0), MOD(CurrentMonth, 12) + 1, 1))} -> -300 | M13: =J13+K13+L13 -> 0.011 | O13: Bar Night | P13: {=INDEX(Rollovers[BOM], MATCH(1, (Rollovers[Month]=CurrentMonth)*(Rollovers[Year]=CurrentYear)*(Rollovers[Expense]=O13), 0))} -> 165.47 | Q13: =_xlfn.LET( _xlpm.CurrDate, DATE(CurrentYear,CurrentMonth,1), _xlpm.Result, SUMIFS( BudgetHistory[Amount], BudgetHistory[Expense], O13, BudgetHistory[StartDate], "<=" & _xlpm.CurrDate, BudgetHistory[EndDate], ">=" & _xlpm.CurrDate ), IF(_xlpm.Result = 0, INDEX(ExpenseBudgets, MATCH(O13, Expenses!$A:$A, 0)), _xlpm.Result) ) -> 50 | R13: {=SUMIFS(TransactionsAmount, TransactionExpenseType, O13, TransactionDates, ">=" & DATE(CurrentYear, CurrentMonth, 1), TransactionDates, "<" & DATE(CurrentYear + IF(CurrentMonth=12, 1, 0), MOD(CurrentMonth, 12) + 1, 1))} -> 0 | S13: =P13+Q13+R13 -> 215.47
C14: Hydro | D14: {=INDEX(Rollovers[BOM], MATCH(1, (Rollovers[Month]=CurrentMonth)*(Rollovers[Year]=CurrentYear)*(Rollovers[Expense]=C14), 0))} -> 7.47 | E14: =_xlfn.LET( _xlpm.CurrDate, DATE(CurrentYear,CurrentMonth,1), _xlpm.Result, SUMIFS( BudgetHistory[Amount], BudgetHistory[Expense], C14, BudgetHistory[StartDate], "<=" & _xlpm.CurrDate, BudgetHistory[EndDate], ">=" & _xlpm.CurrDate ), IF(_xlpm.Result = 0, INDEX(ExpenseBudgets, MATCH(C14, Expenses!$A:$A, 0)), _xlpm.Result) ) -> 100 | F14: {=SUMIFS(TransactionsAmount, TransactionExpenseType, C14, TransactionDates, ">=" & DATE(CurrentYear, CurrentMonth, 1), TransactionDates, "<" & DATE(CurrentYear + IF(CurrentMonth=12, 1, 0), MOD(CurrentMonth, 12) + 1, 1))} -> -104.57 | G14: =D14+E14+F14 -> 2.9 | I14: Land Taxes | J14: {=INDEX(Rollovers[BOM], MATCH(1, (Rollovers[Month]=CurrentMonth)*(Rollovers[Year]=CurrentYear)*(Rollovers[Expense]=I14), 0))} -> 35.46 | K14: =_xlfn.LET( _xlpm.CurrDate, DATE(CurrentYear,CurrentMonth,1), _xlpm.Result, SUMIFS( BudgetHistory[Amount], BudgetHistory[Expense], I14, BudgetHistory[StartDate], "<=" & _xlpm.CurrDate, BudgetHistory[EndDate], ">=" & _xlpm.CurrDate ), IF(_xlpm.Result = 0, INDEX(ExpenseBudgets, MATCH(I14, Expenses!$A:$A, 0)), _xlpm.Result) ) -> 294 | L14: {=SUMIFS(TransactionsAmount, TransactionExpenseType, I14, TransactionDates, ">=" & DATE(CurrentYear, CurrentMonth, 1), TransactionDates, "<" & DATE(CurrentYear + IF(CurrentMonth=12, 1, 0), MOD(CurrentMonth, 12) + 1, 1))} -> -287 | M14: =J14+K14+L14 -> 42.46 | O14: House Fund | P14: {=INDEX(Rollovers[BOM], MATCH(1, (Rollovers[Month]=CurrentMonth)*(Rollovers[Year]=CurrentYear)*(Rollovers[Expense]=O14), 0))} -> 931.69 | Q14: =_xlfn.LET( _xlpm.CurrDate, DATE(CurrentYear,CurrentMonth,1), _xlpm.Result, SUMIFS( BudgetHistory[Amount], BudgetHistory[Expense], O14, BudgetHistory[StartDate], "<=" & _xlpm.CurrDate, BudgetHistory[EndDate], ">=" & _xlpm.CurrDate ), IF(_xlpm.Result = 0, INDEX(ExpenseBudgets, MATCH(O14, Expenses!$A:$A, 0)), _xlpm.Result) ) -> 300 | R14: {=SUMIFS(TransactionsAmount, TransactionExpenseType, O14, TransactionDates, ">=" & DATE(CurrentYear, CurrentMonth, 1), TransactionDates, "<" & DATE(CurrentYear + IF(CurrentMonth=12, 1, 0), MOD(CurrentMonth, 12) + 1, 1))} -> 0 | S14: =P14+Q14+R14 -> 1231.69
O15: Health | P15: {=INDEX(Rollovers[BOM], MATCH(1, (Rollovers[Month]=CurrentMonth)*(Rollovers[Year]=CurrentYear)*(Rollovers[Expense]=O15), 0))} -> 2165.31 | Q15: =_xlfn.LET( _xlpm.CurrDate, DATE(CurrentYear,CurrentMonth,1), _xlpm.Result, SUMIFS( BudgetHistory[Amount], BudgetHistory[Expense], O15, BudgetHistory[StartDate], "<=" & _xlpm.CurrDate, BudgetHistory[EndDate], ">=" & _xlpm.CurrDate ), IF(_xlpm.Result = 0, INDEX(ExpenseBudgets, MATCH(O15, Expenses!$A:$A, 0)), _xlpm.Result) ) -> 150 | R15: {=SUMIFS(TransactionsAmount, TransactionExpenseType, O15, TransactionDates, ">=" & DATE(CurrentYear, CurrentMonth, 1), TransactionDates, "<" & DATE(CurrentYear + IF(CurrentMonth=12, 1, 0), MOD(CurrentMonth, 12) + 1, 1))} -> -3 | S15: =P15+Q15+R15 -> 2312.31
R17: Subtotal | S17: =SUM(S3:S14) -> 4588.92
R18: Accrued | S18: =AccruedTotal -> 6107.4004
R19: Total | S19: =S17+S18 -> 10696.32
R20: Bank Amount | S20: 11122.34
R21: Balance | S21: =S17+S18-S20 -> -426.01964
R22: Melissa Loan | S22: 4000

Sheet Expenses
A1: Expense Type | B1: Budget | C1: Category | D1: Required | E1: Account | F1: Init | G1: MLB
A2: Mortgage | B2: =443.25*26/12 -> 960.375 | C2: Home | D2: Need | E2: Chequing | F2: 75 | G2: 960.38
A3: Land Taxes | B3: 302 | C3: Home | D3: Need | E3: Chequing | F3: 8 | G3: 302
A4: Home Insurance | B4: 230.75 | C4: Home | D4: Need | E4: Chequing | F4: 0 | G4: 230.7
A5: Hydro | B5: 100 | C5: Home | D5: Need | E5: Chequing | F5: -50 | G5: 100
A6: Heat/Gas | B6: 80 | C6: Home | D6: Need | E6: Chequing | F6: 5 | G6: 80
A7: Sewer/Water | B7: 85 | C7: Home | D7: Need | E7: Chequing | F7: 20 | G7: 85
A8: Phone Bills | B8: 125.43 | C8: Home | D8: Need | E8: Chequing | F8: 0 | G8: 125.43
A9: Internet Bill | B9: 91.53 | C9: Home | D9: Need | E9: Chequing | F9: 0 | G9: 91.53
A10: Auto Insurance | B10: 221.5 | C10: Vehicle | D10: Need | E10: Chequing | F10: 0 | G10: 221.5
A11: Car Fuel | B11: 200 | C11: Vehicle | D11: Need | E11: Chequing | F11: 696 | G11: 200
A12: Cat Fund | B12: 150 | C12: Personal | D12: Need | E12: Chequing | F12: -56 | G12: 100
A13: Grocery | B13: 600 | C13: Food | D13: Need | E13: Chequing | F13: -212 | G13: 600
A14: Personal Care | B14: 100 | C14: Shopping | D14: Need | E14: Chequing | F14: 26 | G14: 100
A15: Misc Fees | B15: 10 | C15: Other | D15: Need | E15: Chequing | F15: -26 | G15: 10
A16: Ignore | B16: 0 | C16: Other | D16: Need | E16: Chequing | F16: 0
A17: RRSP | B17: =((50*26)+(50*12))/12 -> 158.33333 | C17: Investments | D17: Smart | E17: Chequing | F17: 0 | G17: =ExpenseData[[#This Row],[Budget]] -> 158.33333
A18: Private Insurances | B18: =125.87+125.57 -> 251.44 | C18: Investments | D18: Smart | E18: Chequing | F18: 0 | G18: 251.44
A19: Health | B19: 200 | C19: Personal | D19: Smart | E19: Saving | F19: 657 | G19: 0
A20: Business Line | B20: 150 | C20: Investments | D20: Smart | E20: Chequing | F20: 0 | G20: 0
A21: Car Maintenance | B21: 300 | C21: Vehicle | D21: Smart | E21: Saving | F21: 300.18
A22: House Fund | B22: 300 | C22: Shopping | D22: Smart | E22: Saving | F22: 699
A23: Electronics Fund | B23: 150 | C23: Shopping | D23: Want | E23: Saving
A24: Subscriptions | B24: =((25.98*12)/6*2)/12 -> 8.66 | C24: Leisure | D24: Want | E24: Chequing | F24: 0 | G24: 8.66
A25: Vacation Fund | B25: 200 | C25: Travel | D25: Want | E25: Saving | F25: 1769.34
A26: Weekend Trips | B26: 140 | C26: Travel | D26: Want | E26: Saving | F26: 184.49
A27: RV Fund | B27: 100 | C27: Leisure | D27: Want | E27: Saving | F27: 68.45
A28: Date Night | B28: 50 | C28: Food | D28: Want | E28: Saving | F28: 117.83
A29: Fast Food | B29: 50 | C29: Food | D29: Want | E29: Chequing | F29: 46
A30: Clothes | B30: 140 | C30: Shopping | D30: Want | E30: Saving | F30: 529.4
A31: Shopping Fund | B31: 140 | C31: Shopping | D31: Want | E31: Chequing | F31: 62
A32: Gifts | B32: 200 | C32: Shopping | D32: Need | E32: Saving | F32: 3.57 | G32: 50
A33: Entertainment | B33: 150 | C33: Leisure | D33: Want | E33: Saving | F33: 234.8
A34: Gym | B34: =65.52/12+9.03*2 -> 23.52 | C34: Personal | D34: Want | E34: Chequing | F34: -325.53 | G34: 0
A35: Bar Night | B35: 50 | C35: Leisure | D35: Want | E35: Saving | F35: 247.56
A36: Alcohol | B36: 130 | C36: Leisure | D36: Want | E36: Saving | F36: 141.45 | G36: 50
A37: Weed | B37: 65 | C37: Leisure | D37: Want | E37: Chequing | F37: 14 | G37: 0
A38: Allowances | B38: 400 | C38: Personal | D38: Want | E38: Chequing | F38: 0 | G38: 0
A39: Lottery | B39: 20 | C39: Leisure | D39: Want | E39: Chequing | F39: 0
A40: Accruals | B40: =AccrualsMonthly -> 797.34423 | C40: Accruals | D40: Want | E40: Saving | F40: 0
A42: Total | B42: =SUBTOTAL(109,ExpenseData[Budget]) -> 7430.8826
G44: =SUM(G2:G43) -> 3724.9733

Sheet Income
A1: Partner | B1: Source | C1: Salary | D1: Gross | E1: Net | F1: Hours | G1: Hourly Rate | H1: Income Rate | I1: Deductions | J1: Monthly | K1: Yearly | L1: Column1
A2: Steven | B2: Paycheck | C2: =IncomeData[[#This Row],[Gross]]*26 -> 94094 | D2: 3619 | E2: 2388.1 | F2: 70 | G2: =IncomeData[[#This Row],[Gross]]/IncomeData[[#This Row],[Hours]] -> 51.7 | H2: =IncomeData[[#This Row],[Net]]/IncomeData[[#This Row],[Hours]] -> 34.115714 | I2: =1-(IncomeData[[#This Row],[Net]]/IncomeData[[#This Row],[Gross]]) -> 0.34012158 | J2: =IncomeData[[#This Row],[Yearly]]/12 -> 5174.2167 | K2: =IncomeData[[#This Row],[Net]]*26 -> 62090.6 | L2: =IncomeData[[#This Row],[Yearly]]/IncomeData[[#Totals],[Yearly]] -> 0.64402428
A3: Melissa | B3: Paycheck | C3: 46691.47 | D3: =IncomeData[[#This Row],[Salary]]/26 -> 1795.8258 | E3: 1319.99 | F3: 75 | G3: =IncomeData[[#This Row],[Gross]]/IncomeData[[#This Row],[Hours]] -> 23.944344 | H3: =IncomeData[[#This Row],[Net]]/IncomeData[[#This Row],[Hours]] -> 17.599867 | I3: =1-(IncomeData[[#This Row],[Net]]/IncomeData[[#This Row],[Gross]]) -> 0.26496767 | J3: =IncomeData[[#This Row],[Yearly]]/12 -> 2859.9783 | K3: =IncomeData[[#This Row],[Net]]*26 -> 34319.74 | L3: =IncomeData[[#This Row],[Yearly]]/IncomeData[[#Totals],[Yearly]] -> 0.35597572
B4: Totals or Average: | C4: =SUBTOTAL(109,IncomeData[Salary]) -> 140785.47 | D4: =SUBTOTAL(109,IncomeData[Gross]) -> 5414.8258 | E4: =SUBTOTAL(109,IncomeData[Net]) -> 3708.09 | F4: =SUBTOTAL(101,IncomeData[Hours]) -> 72.5 | G4: =SUBTOTAL(101,IncomeData[Hourly Rate]) -> 37.822172 | H4: =SUBTOTAL(101,IncomeData[Income Rate]) -> 25.85779 | I4: =SUBTOTAL(101,IncomeData[Deductions]) -> 0.30254463 | J4: =SUBTOTAL(109,IncomeData[Monthly]) -> 8034.195 | K4: =SUBTOTAL(109,IncomeData[Yearly]) -> 96410.34

Sheet Accruals
A1: Item | B1: Start Date | C1: Finish Date | D1: Budget | E1: Deposit | F1: Accrued To Date | G1: Monthly Contribution | H1: Months Accrued | I1: Months Start To End | J1: Days Accrued | K1: Starting Next Month | L1: Ended | N1: Monthly Leftover | O1: =MonthlyLeftover -> 603.31244
A2: Tub Maintenance - quote needed | B2: 45870 | C2: 46054 | D2: 1000 | E2: 0 | F2: =IFERROR(H2*G2+E2,0) -> 857.14286 | G2: =IFERROR((D2-E2)/I2,0) -> 142.85714 | H2: =IFERROR(DATEDIF(B2,TODAY(),"M")+1,0) -> 6 | I2: =DATEDIF(B2,C2,"M")+1 -> 7 | J2: =IFERROR(DATEDIF(B2,TODAY(),"D"),DATEDIF(TODAY(),B2,"D")*-1) -> 160 | K2: =IFERROR(_xlfn.XOR(J2>=-31,L2),FALSE) -> TRUE | L2: =IFERROR(DATEDIF(C2,TODAY(),"D")>=0,FALSE) -> FALSE
A3: Appliances | B3: 45870 | C3: 46388 | D3: 6000 | E3: 0 | F3: =IFERROR(H3*G3+E3,0) -> 2000 | G3: =IFERROR((D3-E3)/I3,0) -> 333.33333 | H3: =IFERROR(DATEDIF(B3,TODAY(),"M")+1,0) -> 6 | I3: =DATEDIF(B3,C3,"M")+1 -> 18 | J3: =IFERROR(DATEDIF(B3,TODAY(),"D"),DATEDIF(TODAY(),B3,"D")*-1) -> 160 | K3: =IFERROR(_xlfn.XOR(J3>=-31,L3),FALSE) -> TRUE | L3: =IFERROR(DATEDIF(C3,TODAY(),"D")>=0,FALSE) -> FALSE | O3: this number as of 30/11/2025: 347.43
A4: Melissa Loan Repay | B4: 45931 | C4: 46388 | D4: 4000 | E4: 0 | F4: =IFERROR(H4*G4+E4,0) -> 1000 | G4: =IFERROR((D4-E4)/I4,0) -> 250 | H4: =IFERROR(DATEDIF(B4,TODAY(),"M")+1,0) -> 4 | I4: =DATEDIF(B4,C4,"M")+1 -> 16 | J4: =IFERROR(DATEDIF(B4,TODAY(),"D"),DATEDIF(TODAY(),B4,"D")*-1) -> 99 | K4: =IFERROR(_xlfn.XOR(J4>=-31,L4),FALSE) -> TRUE | L4: =IFERROR(DATEDIF(C4,TODAY(),"D")>=0,FALSE) -> FALSE
A5: Surplus Fund :) | B5: 46023 | C5: 46023 | D5: =E5+114.42 -> 1377.18 | E5: =(286.02+209.1+255.88+255.88+255.88) -> 1262.76 | F5: =IFERROR(H5*G5+E5,0) -> 1377.18 | G5: =IFERROR((D5-E5)/I5,0) -> 114.42 | H5: =IFERROR(DATEDIF(B5,TODAY(),"M")+1,0) -> 1 | I5: =DATEDIF(B5,C5,"M")+1 -> 1 | J5: =IFERROR(DATEDIF(B5,TODAY(),"D"),DATEDIF(TODAY(),B5,"D")*-1) -> 7 | K5: =IFERROR(_xlfn.XOR(J5>=-31,L5),FALSE) -> FALSE | L5: =IFERROR(DATEDIF(C5,TODAY(),"D")>=0,FALSE) -> TRUE
A6: Shane Wedding Fund | B6: 45992 | C6: 46204 | D6: 800 | E6: 230.77 | F6: =IFERROR(H6*G6+E6,0) -> 373.0775 | G6: =IFERROR((D6-E6)/I6,0) -> 71.15375 | H6: =IFERROR(DATEDIF(B6,TODAY(),"M")+1,0) -> 2 | I6: =DATEDIF(B6,C6,"M")+1 -> 8 | J6: =IFERROR(DATEDIF(B6,TODAY(),"D"),DATEDIF(TODAY(),B6,"D")*-1) -> 38 | K6: =IFERROR(_xlfn.XOR(J6>=-31,L6),FALSE) -> TRUE | L6: =IFERROR(DATEDIF(C6,TODAY(),"D")>=0,FALSE) -> FALSE
A7: Sliding Patio Door | B7: 46082 | C7: 46143 | D7: 2500 | E7: 500 | F7: =IFERROR(H7*G7+E7,0) -> 500 | G7: =IFERROR((D7-E7)/I7,0) -> 666.66667 | H7: =IFERROR(DATEDIF(B7,TODAY(),"M")+1,0) -> 0 | I7: =DATEDIF(B7,C7,"M")+1 -> 3 | J7: =IFERROR(DATEDIF(B7,TODAY(),"D"),DATEDIF(TODAY(),B7,"D")*-1) -> -52 | K7: =IFERROR(_xlfn.XOR(J7>=-31,L7),FALSE) -> FALSE | L7: =IFERROR(DATEDIF(C7,TODAY(),"D")>=0,FALSE) -> FALSE
A8: Frank Wedding Fund | B8: 46082 | C8: 46266 | D8: 800 | E8: 0 | F8: =IFERROR(H8*G8+E8,0) -> 0 | G8: =IFERROR((D8-E8)/I8,0) -> 114.28571 | H8: =IFERROR(DATEDIF(B8,TODAY(),"M")+1,0) -> 0 | I8: =DATEDIF(B8,C8,"M")+1 -> 7 | J8: =IFERROR(DATEDIF(B8,TODAY(),"D"),DATEDIF(TODAY(),B8,"D")*-1) -> -52 | K8: =IFERROR(_xlfn.XOR(J8>=-31,L8),FALSE) -> FALSE | L8: =IFERROR(DATEDIF(C8,TODAY(),"D")>=0,FALSE) -> FALSE
A9: Mattress | B9: 46174 | C9: 46357 | D9: 1500 | E9: 0 | F9: =IFERROR(H9*G9+E9,0) -> 0 | G9: =IFERROR((D9-E9)/I9,0) -> 214.28571 | H9: =IFERROR(DATEDIF(B9,TODAY(),"M")+1,0) -> 0 | I9: =DATEDIF(B9,C9,"M")+1 -> 7 | J9: =IFERROR(DATEDIF(B9,TODAY(),"D"),DATEDIF(TODAY(),B9,"D")*-1) -> -144 | K9: =IFERROR(_xlfn.XOR(J9>=-31,L9),FALSE) -> FALSE | L9: =IFERROR(DATEDIF(C9,TODAY(),"D")>=0,FALSE) -> FALSE
A10: Extra Month Bank Cushion | B10: 46388 | C10: 46539 | D10: 4000 | E10: 0 | F10: =IFERROR(H10*G10+E10,0) -> 0 | G10: =IFERROR((D10-E10)/I10,0) -> 666.66667 | H10: =IFERROR(DATEDIF(B10,TODAY(),"M")+1,0) -> 0 | I10: =DATEDIF(B10,C10,"M")+1 -> 6 | J10: =IFERROR(DATEDIF(B10,TODAY(),"D"),DATEDIF(TODAY(),B10,"D")*-1) -> -358 | K10: =IFERROR(_xlfn.XOR(J10>=-31,L10),FALSE) -> FALSE | L10: =IFERROR(DATEDIF(C10,TODAY(),"D")>=0,FALSE) -> FALSE
A11: Vehicle Deposit | B11: 46388 | C11: 47484 | D11: 20000 | E11: 0 | F11: =IFERROR(H11*G11+E11,0) -> 0 | G11: =IFERROR((D11-E11)/I11,0) -> 540.54054 | H11: =IFERROR(DATEDIF(B11,TODAY(),"M")+1,0) -> 0 | I11: =DATEDIF(B11,C11,"M")+1 -> 37 | J11: =IFERROR(DATEDIF(B11,TODAY(),"D"),DATEDIF(TODAY(),B11,"D")*-1) -> -358 | K11: =IFERROR(_xlfn.XOR(J11>=-31,L11),FALSE) -> FALSE | L11: =IFERROR(DATEDIF(C11,TODAY(),"D")>=0,FALSE) -> FALSE
B12: 46508 | C12: 47484 | D12: 0 | E12: 0 | F12: =IFERROR(H12*G12+E12,0) -> 0 | G12: =IFERROR((D12-E12)/I12,0) -> 0 | H12: =IFERROR(DATEDIF(B12,TODAY(),"M")+1,0) -> 0 | I12: =DATEDIF(B12,C12,"M")+1 -> 33 | J12: =IFERROR(DATEDIF(B12,TODAY(),"D"),DATEDIF(TODAY(),B12,"D")*-1) -> -478 | K12: =IFERROR(_xlfn.XOR(J12>=-31,L12),FALSE) -> FALSE | L12: =IFERROR(DATEDIF(C12,TODAY(),"D")>=0,FALSE) -> FALSE
A13: Brandon Wedding Fund | B13: 46539 | C13: 46905 | D13: 1000 | E13: 0 | F13: =IFERROR(H13*G13+E13,0) -> 0 | G13: =IFERROR((D13-E13)/I13,0) -> 76.923077 | H13: =IFERROR(DATEDIF(B13,TODAY(),"M")+1,0) -> 0 | I13: =DATEDIF(B13,C13,"M")+1 -> 13 | J13: =IFERROR(DATEDIF(B13,TODAY(),"D"),DATEDIF(TODAY(),B13,"D")*-1) -> -509 | K13: =IFERROR(_xlfn.XOR(J13>=-31,L13),FALSE) -> FALSE | L13: =IFERROR(DATEDIF(C13,TODAY(),"D")>=0,FALSE) -> FALSE
D14: =SUM(D2:D13) -> 42977.18 | E14: =SUM(E2:E13) -> 1993.53 | F14: =SUM(F2:F13) -> 6107.4004 | G14: =SUMIFS(G2:G13,K2:K13,"=TRUE",L2:L13,"=FALSE") -> 797.34423

Sheet Transactions
A1: ID | B1: Month | C1: Year | D1: Date | E1: Account | F1: Expense Type | G1: Amount | H1: Description | I1: Memo
A2: 4204f7491c41d61827487eaaf47b33ef8f73328e321a05887528527074480053 | B2: 8 | C2: 2023 | D2: 45166 | E2: Credit Line (7001) | F2: Expense Type | G2: -10000 | H2: WWW TFR TIN0-08127
A3: 040b39a142ced30b25698ae2e75a838a4d0599988ced4b9b3561e21f11e9769f | B3: 9 | C3: 2023 | D3: 45170 | E3: Credit Line (7001) | F3: Expense Type | G3: 900 | H3: WWW PMT TIN0-06504
A4: 80d1e18e5da3456892bcb9540ecc617e42694833d0090cc0bf286eec590a6d99 | B4: 9 | C4: 2023 | D4: 45175 | E4: Credit Line (7001) | F4: Expense Type | G4: -1372 | H4: WWW TFR TIN0-07556
A5: 439075b680849869b8d6a01a7badc318c3056578e8a04e4c720e304d73635934 | B5: 9 | C5: 2023 | D5: 45191 | E5: Credit Line (7001) | F5: Misc Fees | G5: 0 | H5: INTEREST PAYMENT 81.67
A6: 36b0dc76a91aeeb71037264ae3330b2d95735fed2cd64401564cd45827e6313f | B6: 9 | C6: 2023 | D6: 45191 | E6: Credit Line (7001) | F6: Misc Fees | G6: 0 | H6: LOANPROTECTOR INSURANCE PREMIUM 8.28
A7: 47d0f2255d221bd4f22f1b99eb878e09d038eda76d022e9b47be93cfa8b68ffc | B7: 10 | C7: 2023 | D7: 45202 | E7: Credit Line (7001) | F7: Expense Type | G7: 900 | H7: WWW PMT TIN0-03778
A8: 94329474b1b1f472f109ec60c15accfbf1c7a1738fd03bc41121b1f65057d64f | B8: 10 | C8: 2023 | D8: 45211 | E8: Credit Line (7001) | F8: Expense Type | G8: -89.95 | H8: WWW TFR TIN0-09559
A9: 10e4e1d138b5ac14e4709d508713e8dd481a51d83ea2775c025c1027e5c59bd4 | B9: 10 | C9: 2023 | D9: 45222 | E9: Credit Line (7001) | F9: Misc Fees | G9: 0 | H9: INTEREST PAYMENT 99.28
A10: 19d623ca5a5e8b14b37b371a04f96de323b90f89f3e64da7a237354518116261 | B10: 10 | C10: 2023 | D10: 45222 | E10: Credit Line (7001) | F10: Misc Fees | G10: 0 | H10: LOANPROTECTOR INSURANCE PREMIUM 10.08
A11: 7cf3a7950e670064f09144c39e59ff88e5c7750e840e6c535a8b9996170ef6dc | B11: 11 | C11: 2023 | D11: 45231 | E11: Credit Line (7001) | F11: Expense Type | G11: 900 | H11: WWW PMT TIN0-02373
B12: 12 | C12: 2025 | D12: 45995 | E12: Shared Savings (9290) | F12: Entertainment | G12: =(15.31+8.45+8.9)*-1 -> -32.66 | H12: etransfer from savings to steven for xmas date (dollarama + sobeys + pizza pizza) | I12: To be deleted with actual transaction record matching this amount
A13: 6965f6f7d765585662aeeb5518db0bf08f1e98beef77293b27f984049ac0b89c | B13: 11 | C13: 2023 | D13: 45252 | E13: Credit Line (7001) | F13: Misc Fees | G13: 0 | H13: INTEREST PAYMENT 87.45
A14: 7e072ea4b8a9054213f0d7382ac8617a1cf95c54148066866016a6922458dee2 | B14: 11 | C14: 2023 | D14: 45252 | E14: Credit Line (7001) | F14: Misc Fees | G14: 0 | H14: LOANPROTECTOR INSURANCE PREMIUM 8.88
A15: 2ba5fbacde633be4754b316bd5d68bc6a67a225f2a1e5a07cadc378fbd985618 | B15: 12 | C15: 2023 | D15: 45261 | E15: Credit Line (7001) | F15: Expense Type | G15: 800 | H15: WWW PMT TIN0-05949
A16: bd39a0650ed3a3394adf405af30cfee9f5c0b69b32105311db653e9fca46a22d | B16: 12 | C16: 2023 | D16: 45282 | E16: Credit Line (7001) | F16: Misc Fees | G16: 0 | H16: INTEREST PAYMENT 79.41
A17: 88cf71a7de9449ee2765e0c484fc8982f574f74f90e97fa7648af5a82f71c54e | B17: 12 | C17: 2023 | D17: 45282 | E17: Credit Line (7001) | F17: Misc Fees | G17: 0 | H17: LOANPROTECTOR INSURANCE PREMIUM 8.07
A18: c351bea88f86241a0c1e976da997091a13b323478f47e68fea786b50dbf8c561 | B18: 12 | C18: 2023 | D18: 45287 | E18: Shared Chequings (6838) | F18: RRSP | G18: 0 | H18: INVESTMENT IG FIN SER SFGI
A19: fb38166c3b634d5fd63faaf55f0628dfa958c820d1e4151114f38732b11e56e4 | B19: 12 | C19: 2023 | D19: 45287 | E19: Shared Chequings (6838) | F19: Gym | G19: 0 | H19: MISC PAYMENT Fit4less
A20: 1aca83f831d0510becef42c72394bffcf95f28f7594fa408004daa93f5b0cfb8 | B20: 12 | C20: 2023 | D20: 45287 | E20: Shared Savings (9290) | F20: Expense Type | G20: 0 | H20: WWW TRF DDA - 4791
A21: 43147baac32118c66a89008d81b6e84236198ec9ddcbb70b4ef3f4fe5292ba7a | B21: 12 | C21: 2023 | D21: 45287 | E21: Shared Chequings (6838) | F21: Auto Insurance | G21: 0 | H21: AUTO INSURANCE ALLSTATE INS.
A22: 5276906ccd4297a677cdf03dd2c85df62a85d44e4dc7e725af375d7b6595e3ac | B22: 12 | C22: 2023 | D22: 45289 | E22: Shared Chequings (6838) | F22: Mortgage | G22: 0 | H22: MISC PAYMENT MORTGAGE PAYMEN
A23: 5a5f085c3c6bdea35357567bc2a1c58e219c175c6829db1ec974c8042de46b4c | B23: 12 | C23: 2023 | D23: 45289 | E23: Shared Chequings (6838) | F23: Ignore | G23: 0 | H23: PAYROLL DEPOSIT Thinking Big In
A24: 6e6692899146d41758d61f5a4ef24e6544b1f200842c95f4c602aca7ea84393a | B24: 1 | C24: 2024 | D24: 45293 | E24: Shared Chequings (6838) | F24: RRSP | G24: 0 | H24: MUTUAL FUNDS SPECIAL DEPOSIT
... A84: 357d345823c2c43b04a9340f16b3183b385543a3d7938e09f146995d12994ec8 | B84: 2 | C84: 2024 | D84: 45329 | E84: Shared Visa (3292) | F84: Subscriptions | G84: -25.98 | H84: GOOGLE *YouTubePremium g.co/helppay#NS
A85: 24d00da5a4f7b081b4cf3fe5648d34a41d30c7ae28364294a484a2a26699d798 | B85: 2 | C85: 2024 | D85: 45330 | E85: Shared Chequings (6838) | F85: Private Insurances | G85: -125.87 | H85: LIFE INSURANCE CANLIFE-ING | I85: Steve's life insurance
A86: 4e4c9b74ddcd430f4980ee6be15d83821d28b6c10c2eb5d5ac3588e977ebffe5 | B86: 2 | C86: 2024 | D86: 45330 | E86: Shared Visa (3292) | F86: Grocery | G86: -17.89 | H86: WAL-MART SUPERCENTER#3063NORTH BAY ON
A87: 520a7e51ff0f3fd2d925e4b9d39a1ebbcaababaa9c0fa9e3cd2d32bee6a5c3d4 | B87: 2 | C87: 2024 | D87: 45331 | E87: Shared Chequings (6838) | F87: Mortgage | G87: -443.25 | H87: MISC PAYMENT MORTGAGE PAYMEN
A88: 2eb23847ab800094218b6ea594ef08f997a86e9804a0d447ae773470bd6183a7 | B88: 2 | C88: 2024 | D88: 45331 | E88: Shared Visa (3292) | F88: Internet Bill | G88: -84.75 | H88: VIRGIN PLUS VERDUN QC
A89: cfbc564116025c8f6b541712f031da1f1d7a89b7e9d30a36de4cf728ded21ac4 | B89: 2 | C89: 2024 | D89: 45331 | E89: Shared Chequings (6838) | F89: Ignore | G89: 2048.43 | H89: PAYROLL DEPOSIT Thinking Big In
A90: f90d5ddd48a1dc776cde86436aff75db09bb8bba884207dce0e462a2940c5506 | B90: 2 | C90: 2024 | D90: 45331 | E90: Shared Visa (3292) | F90: Entertainment | G90: -49.38 | H90: SOBEYS #715 NORTH BAY ON
A91: db02da299527f06ddf9da392794b74b7c8c9131ac6040a46f5081639a3668909 | B91: 2 | C91: 2024 | D91: 45334 | E91: Shared Chequings (6838) | F91: Sewer/Water | G91: -70.57 | H91: Payment WWW PAYMENT - 7074 NORTH BAY WAT
A92: d01710ea01bcf0ff2be41bffa724ca68b92d6801250593a345b153f10263e471 | B92: 2 | C92: 2024 | D92: 45334 | E92: Shared Visa (3292) | F92: Grocery | G92: -112 | H92: WAL-MART SUPERCENTER#3063NORTH BAY ON
A93: 3da451d4678209f030de1eba59abc5ccde138eb2995928d26a62959b09f61b29 | B93: 2 | C93: 2024 | D93: 45336 | E93: Shared Visa (3292) | F93: Date Night | G93: -35.96 | H93: B.Y TAKE OUT NORTH BAY ON
A94: 2bd5c0abcc96ed278b3863025bf5b425e71e40b048a1bcbf89ebe275d123030b | B94: 2 | C94: 2024 | D94: 45337 | E94: Shared Chequings (6838) | F94: Private Insurances | G94: -125.57 | H94: INSURANCE CANADALIFE | I94: Critical illness
A95: ec130f7198722071a9e79a95e82ea3e95eaf3b820ab3ca59d8075371050ac82d | B95: 2 | C95: 2024 | D95: 45337 | E95: Shared Chequings (6838) | F95: Land Taxes | G95: -280 | H95: MISC PAYMENT CITY OF NORTH B
A96: 0174e8df94bf7d2958950d4b218f0aaf04a5bddbfa56a5b89770a490753659e2 | B96: 2 | C96: 2024 | D96: 45337 | E96: Shared Chequings (6838) | F96: Ignore | G96: 1231.84 | H96: PAYROLL DEPOSIT ClaimSecure Inc | K96: Done
A97: 12e83900a72e42d4dcf9cbc319a70bb1271af0f9f537759f950ea344edee96ce | B97: 2 | C97: 2024 | D97: 45337 | E97: Shared Visa (3292) | F97: Ignore | G97: -90 | H97: THE MASSAGE THERAPY CLININORTH BAY ON
A98: 594bf83b44e7dce3bac0e5e3e116c0ed06fda5819f4ff8ccf1a199159f8871cf | B98: 2 | C98: 2024 | D98: 45337 | E98: Shared Visa (3292) | F98: Fast Food | G98: -7.55 | H98: McDonalds 12016 NORTH BAY ON
A99: 1e2d5b914855d65cb14e1dfb9a283ea2c7f1a1e4bcbce364ef5d8fc231fec259 | B99: 2 | C99: 2024 | D99: 45338 | E99: Shared Visa (3292) | F99: Phone Bills | G99: -96.71 | H99: KOODO MOBILE PAC 111-1111111 AB
A100: aada3afb52652c4bf3e91a9778dfddaf3bc8529c9318ac03487da5a230423ef0 | B100: 2 | C100: 2024 | D100: 45338 | E100: Shared Visa (3292) | F100: Ignore | G100: 1615.75 | H100: AUTOMATIC PAYMENT - THANK YOU
A101: 0387dd5bd0b5550c03af023dbfe909eedcf04cd317fe2f686af46fb45238e9e6 | B101: 2 | C101: 2024 | D101: 45339 | E101: Shared Visa (3292) | F101: Shopping Fund | G101: -29.28 | H101: DOLLARAMA #1202 NORTH BAY ON
A102: 8230d8bb43cab71d06c57c9bd67fd8d41e8e3e6840fc71d2ec0992c8039b5b4f | B102: 2 | C102: 2024 | D102: 45339 | E102: Shared Visa (3292) | F102: Grocery | G102: -76.73 | H102: ALAN & MICHELLE'S NF N NORTH BAY ON
A103: e2f59054859bd7f4ba7b1c184d3e55d9f44bf0bc556e33cdf350be3727122abd | B103: 2 | C103: 2024 | D103: 45339 | E103: Shared Visa (3292) | F103: Fast Food | G103: -6.39 | H103: TIM HORTONS #0583 NORTH BAY ON
A104: f8a0e2dbeeea8459ecc3eb6b4d954303256c12b508ec04f6dda8d23736823e4d | B104: 2 | C104: 2024 | D104: 45339 | E104: Shared Visa (3292) | F104: Entertainment | G104: -30.91 | H104: FESTIVAL DU VOYAGEUR INC WINNIPEG MB
A105: fbf56a869554857e8babb13ce5a17106558325714088f4731b64cc73cda96114 | B105: 2 | C105: 2024 | D105: 45339 | E105: Shared Visa (3292) | F105: Entertainment | G105: -42 | H105: FESTIVAL DU VOYAGEUR INC WINNIPEG MB
A106: 98b97ca46f8a12d81109caac5c4b346a0af1b3a714acdf803f18eb14491173da | B106: 2 | C106: 2024 | D106: 45339 | E106: Shared Visa (3292) | F106: Entertainment | G106: -23.75 | H106: JOHNNY GS RESTAURANT WINNIPEG MB
A107: ebc9862b0a94c80d977ecf76fda8ad20fde02aa552db7cb465f3402c000afc2d | B107: 2 | C107: 2024 | D107: 45339 | E107: Shared Visa (3292) | F107: Entertainment | G107: -3.05 | H107: SAFEWAY #4867 WINNIPEG MB
A108: 1de29cfadc7495ae819feeef614ac8fab3f0457d14bf656a4982e8755af84136 | B108: 2 | C108: 2024 | D108: 45339 | E108: Shared Visa (3292) | F108: Car Fuel | G108: -50.94 | H108: PETRO CANADA10499 BURKS FALLS ON
... A133: 0f17dcbe09e8f92320713eaf357b2f0cc2e5aecfafc14e5b58525a6e0fc7a973 | B133: 2 | C133: 2024 | D133: 45350 | E133: Shared Visa (3292) | F133: Entertainment | G133: -24.84 | H133: GALAXY CINEMAS7265QPS NORTH BAY ON
B134: 2 | C134: 2024 | D134: 45351 | E134: Shared Savings (9290) | F134: Vacation Fund | G134: 0.1 | I134: Manual fix
B135: 2 | C135: 2024 | D135: 45351 | E135: Shared Chequings (6838) | F135: Misc Fees | G135: 58.25 | H135: Balance transfer: from credit line to misc fees
A136: 505f05694d1180a5fc98768e41b91c3a44be55ccacb92ef32c0bd6d2a78293ec | B136: 2 | C136: 2024 | D136: 45351 | E136: Shared Chequings (6838) | F136: Ignore | G136: 1307.12 | H136: PAYROLL DEPOSIT ClaimSecure Inc
A137: 96eae758753f65b0f01af25f24d2baeee3ca18dbe608bfa1b65e58a742a3b940 | B137: 2 | C137: 2024 | D137: 45351 | E137: Shared Chequings (6838) | F137: Ignore | G137: 17.52 | H137: Transfer WWW TRANSFER - 4841
A138: edfc6dafd9921bbb2354f8134033695fbabdc22281ab5bd511bb66ecb349115e | B138: 2 | C138: 2024 | D138: 45351 | E138: Shared Savings (9290) | F138: Ignore | G138: -17.52 | H138: WWW TRF DDA - 4841
B139: 2 | C139: 2024 | D139: 45351 | E139: Shared Chequings (6838) | F139: Credit Line | G139: -58.25 | H139: Balance transfer: from credit line to misc fees
A140: 03c3fda3cb1b2d5b78dd19842c32eb34fbf0562d8382ceac14b73d5288bd1354 | B140: 3 | C140: 2024 | D140: 45352 | E140: Shared Chequings (6838) | F140: RRSP | G140: -50 | H140: MUTUAL FUNDS SPECIAL DEPOSIT
A141: 9fc8185c40a7c21fdf5aea608b6c31a52e77706b58fd07d820e059b58c2e4919 | B141: 3 | C141: 2024 | D141: 45352 | E141: Shared Savings (9290) | F141: Misc Fees | G141: 2.51 | H141: DEPOSIT INTEREST
A142: cc5169fd5e72bc2fc30b71616f934f8e17ca902e30cdc6fd402defb20b8069dd | B142: 3 | C142: 2024 | D142: 45352 | E142: Shared Chequings (6838) | F142: Ignore | G142: 790.37 | H142: Transfer WWW TRANSFER - 0437
A143: 1896058914a24925a6786d556162462c59c5f8e15bc55a7d91be2754d1c03b02 | B143: 3 | C143: 2024 | D143: 45352 | E143: Shared Savings (9290) | F143: Ignore | G143: 2110 | H143: Transfer WWW TRANSFER - 7844
A144: 76a85c569957e628a0382ba7ea334bd95247bbfc46dfee2758d92c455421e734 | B144: 3 | C144: 2024 | D144: 45352 | E144: Shared Chequings (6838) | F144: Ignore | G144: 73.37 | H144: Transfer WWW TRANSFER - 9716
A145: a85a608867442c84b1d990bed35e3cf302bd40534b14ecba74dade78aa74e7bc | B145: 3 | C145: 2024 | D145: 45352 | E145: Shared Savings (9290) | F145: Ignore | G145: -790.37 | H145: WWW TRF DDA - 0437
A146: 4006c5d016fcfe90b1e1902306da24aa2f9bb0bbcd8e8416b0a6d87d632a59fe | B146: 3 | C146: 2024 | D146: 45352 | E146: Shared Chequings (6838) | F146: Ignore | G146: -2110 | H146: WWW TRF DDA - 7844
A147: 9a0ddd295999a94a5040a3418db751c8713c05ed48456419b0f4ebc15f00278f | B147: 3 | C147: 2024 | D147: 45352 | E147: Shared Visa (3292) | F147: Fast Food | G147: -12.18 | H147: POPEYES #13996 905-856-1500 ON
A148: 92dd28513d37df354d8d5b05a473a6a01073c2ac2bf0348f3833089eae2a092d | B148: 3 | C148: 2024 | D148: 45352 | E148: Shared Chequings (6838) | F148: Credit Line | G148: -400 | H148: Loan Pmt WWW LOAN PMT - 7845
A149: 4f2bee136106227bbd6907b588f0dcfb71eb30a7a653d107968d5e145de9fe9c | B149: 3 | C149: 2024 | D149: 45352 | E149: Credit Line (7001) | F149: Credit Line | G149: 400 | H149: WWW PMT TIN0-07845
A150: 765b2ab7983656ad0f35f50e04228f4d5e32b27e1e853fc4de57d0515f36b567 | B150: 3 | C150: 2024 | D150: 45352 | E150: Shared Visa (3292) | F150: Clothes | G150: -51.72 | H150: TREASURE HUNT NORTH BAY ON
A151: 83c89a1d4498a84b28b1248bac174d6d6d3a0fd1708c642e55ca1df5879a1a00 | B151: 3 | C151: 2024 | D151: 45352 | E151: Shared Chequings (6838) | F151: Allowances | G151: -100 | H151: WWW TRF DDA - 3154
... A153: f529b5ddee27bb06b5e21ed1ca610165888e7abdf4ab1bc33a963145c46f645d | B153: 3 | C153: 2024 | D153: 45353 | E153: Shared Visa (3292) | F153: Grocery | G153: -141.94 | H153: FOOD BASICS 609 NORTH BAY ON
A154: bf70cd3cd8a6c4e8bb57d7424fbe7b218f913c35867148cb970688cd8bd81594 | B154: 3 | C154: 2024 | D154: 45354 | E154: Shared Visa (3292) | F154: Vacation Fund | G154: -45.2 | H154: AMZN Mktp CA*RZ5100161 WWW.AMAZON.CAON | I154: sim card
A155: 29d5dddf173f5cb8ff81d59ed8912d992a730e02ca2fe9ead6a19d0bed62f650 | B155: 3 | C155: 2024 | D155: 45355 | E155: Shared Chequings (6838) | F155: RRSP | G155: -50 | H155: INVESTMENT IG FIN SER SFGI
A156: 0c523b2bad615a795af4b7894516627ae715b817426fe27ded5c89066e2e3aa9 | B156: 3 | C156: 2024 | D156: 45355 | E156: Shared Visa (3292) | F156: Grocery | G156: -21.46 | H156: ALAN & MICHELLE'S NF N NORTH BAY ON
A157: 727ce12c9ab07d205ea46bce77f8f1d4cf7cd2d0286bb911bda1e4f67edffde7 | B157: 3 | C157: 2024 | D157: 45355 | E157: Shared Chequings (6838) | F157: Auto Insurance | G157: -225.75 | H157: AUTO INSURANCE ALLSTATE INS.
A158: f43f7a237e6b94b86107ccac08ecd7d0d61a3433cff344f77473ba97c5fd2c36 | B158: 3 | C158: 2024 | D158: 45356 | E158: Shared Visa (3292) | F158: Personal Hygiene | G158: -35 | H158: SPORTSCUT NORTH BAY ON
A159: dda4b9f8a2b50cf87449a682de748e03a29080633daaf6ef6750e273aa518f05 | B159: 3 | C159: 2024 | D159: 45356 | E159: Shared Visa (3292) | F159: Ignore | G159: 90 | H159: PAYMENT - THANK YOU / PAIEMENT - MERCI
A160: 6acbc5afaeb29cf556086a847187631bb3becc95d34963738b9bde6be20f4fd3 | B160: 3 | C160: 2024 | D160: 45356 | E160: Shared Chequings (6838) | F160: Gym | G160: -9.03 | H160: MISC PAYMENT Fit4less
A161: 19035a01aaa0be8f76aa420655f359ffff55f83a1a07069ef39b191161081f86 | B161: 3 | C161: 2024 | D161: 45357 | E161: Shared Visa (3292) | F161: Vacation Fund | G161: -103.04 | H161: DAYS INNS/DAYSTOP NIAGARA FALLSON
A162: 79a196375c12cecf9c1acbdc109624ddaaa4186a93eee662998b3a5ec3964e11 | B162: 3 | C162: 2024 | D162: 45357 | E162: Shared Visa (3292) | F162: Vacation Fund | G162: -4.61 | H162: TIM HORTONS #0583 NORTH BAY ON
A163: 62210237264b34760d44e4b53d1804a25528637364b7d81278c1b6fd87100f2e | B163: 3 | C163: 2024 | D163: 45357 | E163: Shared Visa (3292) | F163: Health | G163: -22.6 | H163: DR MEGAN SEARS OPTOMETRY NORTH BAY ON
A164: 386b7c54b0a7033e762f349a70e87ed391b4f5564ba430ad47504b06bb7e5bac | B164: 3 | C164: 2024 | D164: 45357 | E164: Shared Visa (3292) | F164: Bar Night | G164: -61.08 | H164: LUCKYS RESTAURANT AND NIAGARA FALLSON
A165: ade23721fd94763f52e0df65cfc872cb42df857786175c37314ae5e45735e55b | B165: 3 | C165: 2024 | D165: 45358 | E165: Shared Visa (3292) | F165: Vacation Fund | G165: -14.79 | H165: GO MART #92 GASSAWAY WV 10.61 USD @ 1.393900000000
A166: bc9c7978ad9b2e45043292b43a81ab23bf3ee086f66f2299e07a3e383572017a | B166: 3 | C166: 2024 | D166: 45358 | E166: Shared Visa (3292) | F166: Vacation Fund | G166: -14.99 | H166: GO MART #96 WYTHEVILLE VA 10.80 USD @ 1.387900000000
... A214: c882e47dc95bacf292c26714c6fbc6fab72db554f1ca6c1bb22fff251cc71220 | B214: 3 | C214: 2024 | D214: 45367 | E214: Shared Visa (3292) | F214: Vacation Fund | G214: -69.67 | H214: ANCHOR BAR RESTAURANT BUFFALO NY 48.92 USD @ 1.424100000000
B215: 3 | C215: 2024 | D215: 45367 | E215: Shared Savings (9290) | F215: Vacation Fund | G215: 2.31 | H215: correction
A216: 38403c9a9d286fa438719a503390c91c4dae3020482f5a5f3a45e823a91488db | B216: 3 | C216: 2024 | D216: 45367 | E216: Shared Visa (3292) | F216: Vacation Fund | G216: -4.8 | H216: MCDONALD'S F3218 WILLIAMSPORT PA 3.38 USD @ 1.420100000000
A217: 25ebc4c6e041e269acdbd5e3608154a29f50d952bffa27daa2b3515e45e40f44 | B217: 3 | C217: 2024 | D217: 45367 | E217: Shared Visa (3292) | F217: Vacation Fund | G217: -6.5 | H217: NF BRIDGE COMMISSION R NIAGARA FALLSON
A218: 0a5fbd5ea2540841217f8377882235dfdb6fa1f623911b80cdad86e1a2fbfbf7 | B218: 3 | C218: 2024 | D218: 45367 | E218: Shared Visa (3292) | F218: Vacation Fund | G218: -4.19 | H218: ONROUTE KING CITY ON
A219: d99d3cd71c0816f7fc619de5b050b752fba0b42b6da3a94b4a3505cfcf59cec8 | B219: 3 | C219: 2024 | D219: 45367 | E219: Shared Visa (3292) | F219: Vacation Fund | G219: -7.33 | H219: SUBWAY (HYBRID) KING CITY ON
A220: 714cb112c3e1b60b10ced804b6e5c8d89908da1d76ed4ff7bf45500d4413f72c | B220: 3 | C220: 2024 | D220: 45367 | E220: Shared Visa (3292) | F220: Vacation Fund | G220: -2.51 | H220: TIM HORTONS #104281 KING CITY ON
A221: b77f95cccec63557e4ce059093613768292328666ef5eefa57c499485d1c5827 | B221: 3 | C221: 2024 | D221: 45367 | E221: Shared Visa (3292) | F221: Vacation Fund | G221: -121.12 | H221: TRADER JOE S #536 AMHERST NY 85.04 USD @ 1.424200000000
A222: d86d8d89d3e5ae2293e0355647d47a279242dc3891a49714de641145b8d21758 | B222: 3 | C222: 2024 | D222: 45367 | E222: Shared Visa (3292) | F222: Phone Bills | G222: -96.71 | H222: KOODO MOBILE PAC 111-1111111 AB
A223: c8da80bf40b7b3cc8f9f7b44842de7f1667f84b0b4b3dd863f014ee779306dbb | B223: 3 | C223: 2024 | D223: 45367 | E223: Shared Visa (3292) | F223: Car Fuel | G223: -46.84 | H223: EXXON DANSVILLE VILLAGE MDANSVIL 32.89 USD @ 1.424100000000
A224: ca914906eb7fc2012adcc95ba74f59fadb6a3e07c6b9f309bd797ec034ef9a84 | B224: 3 | C224: 2024 | D224: 45367 | E224: Shared Visa (3292) | F224: Car Fuel | G224: -31.5 | H224: ONROUTE KING CITY 400 #11KING CITY ON
A225: 0928017aebd287010f87886b4e3f41ef391cb97b48566616a2eaec96efe9a399 | B225: 3 | C225: 2024 | D225: 45367 | E225: Shared Visa (3292) | F225: Bar Night | G225: -312.72 | H225: PREMIER WINES & SPIRITS AMHERST 219.56 USD @ 1.424300000000
A226: acfcbb7ad10bd89c6aaf0f368f12de6ea61320870f5b5ce72dbfae1133391fe2 | B226: 3 | C226: 2024 | D226: 45368 | E226: Shared Visa (3292) | F226: Cat Fund | G226: -36.16 | H226: PRETTYLITTER OTTAWA ON
A227: 83cdf6220c49926e16a6d53ea3eb9b30ce908ba5df39c9aecfd88e5991416a22 | B227: 3 | C227: 2024 | D227: 45369 | E227: Shared Visa (3292) | F227: Shopping Fund | G227: -23.35 | H227: DOLLARAMA # 293 NORTH BAY ON
... A254: bacb94489af23ff4d26579f3b1a28be99eae3ebba06d0fc8e4f13c8f660fff41 | B254: 3 | C254: 2024 | D254: 45378 | E254: Shared Visa (3292) | F254: Health | G254: -680 | H254: DR MEGAN SEARS OPTOMETRY NORTH BAY ON
B255: 3 | C255: 2024 | D255: 45379 | E255: Shared Chequings (6838) | F255: Personal Care | G255: -21.5 | I255: Balancing to auto insurance
A256: af7ea9e4a10e8158b5e4d89792ab5fbabd39213dc46540a1894714b074f44a3c | B256: 3 | C256: 2024 | D256: 45379 | E256: Shared Chequings (6838) | F256: Ignore | G256: 1234.54 | H256: PAYROLL DEPOSIT ClaimSecure Inc
A257: c4e9a6b1e1cff1206853714e7800092bce89c60eeddab4e5cf87631d195e2a86 | B257: 3 | C257: 2024 | D257: 45379 | E257: Shared Chequings (6838) | F257: Ignore | G257: 45.18 | H257: Transfer WWW TRANSFER - 1795
...

Sheet Feature Idea
A1: Transfer between buckets aka enter paired rebalance transactions

Sheet Rollovers
A1: Month | B1: Year | C1: Expense | D1: Expenses | E1: BOM | F1: EOM
A2: 3 | B2: 2024 | C2: Accruals | D2: 0 | E2: 0 | F2: 500
A3: 2 | B3: 2024 | C3: Accruals | D3: 0 | E3: 0 | F3: 0
A4: 4 | B4: 2024 | C4: Accruals | D4: 0 | E4: 500 | F4: 1000
A5: 5 | B5: 2024 | C5: Accruals | D5: 0 | E5: 1000 | F5: 1840.2778
A6: 6 | B6: 2024 | C6: Accruals | D6: 0 | E6: 1840.2778 | F6: 2680.5556
A7: 7 | B7: 2024 | C7: Accruals | D7: 0 | E7: 2680.5556 | F7: 3377.9762
A8: 8 | B8: 2024 | C8: Accruals | D8: 0 | E8: 3377.9762 | F8: 4075.3968
A9: 9 | B9: 2024 | C9: Accruals | D9: 0 | E9: 4075.3968 | F9: 4995.7938
A10: 10 | B10: 2024 | C10: Accruals | D10: 0 | E10: 4995.7938 | F10: 6276.6046
A11: 11 | B11: 2024 | C11: Accruals | D11: 0 | E11: 6276.6046 | F11: 7557.4154
A12: 12 | B12: 2024 | C12: Accruals | D12: 0 | E12: 7557.4154 | F12: 8640.2496
A13: 1 | B13: 2025 | C13: Accruals | D13: 0 | E13: 8640.2496 | F13: 9723.0838
... A265: 11 | B265: 2024 | C265: Electronics Fund | D265: 0 | E265: 0 | F265: 0
A266: 10 | B266: 2024 | C266: Electronics Fund | D266: 0
A267: 12 | B267: 2024 | C267: Electronics Fund | D267: -590.42 | E267: 0 | F267: -440.42
A268: 1 | B268: 2025 | C268: Electronics Fund | D268: 0 | E268: -440.42 | F268: -290.42
A269: 2 | B269: 2025 | C269: Electronics Fund | D269: 0 | E269: -290.42 | F269: -140.42
A270: 3 | B270: 2025 | C270: Electronics Fund | D270: 0 | E270: -140.42 | F270: 9.58
A271: 4 | B271: 2025 | C271: Electronics Fund | D271: -208.22 | E271: 9.58 | F271: -48.64
A272: 5 | B272: 2025 | C272: Electronics Fund | D272: 0 | E272: -48.64 | F272: 101.36
A273: 6 | B273: 2025 | C273: Electronics Fund | D273: 0 | E273: 101.36 | F273: 251.36
A274: 7 | B274: 2025 | C274: Electronics Fund | D274: -82.18 | E274: 251.36 | F274: 319.18
A275: 8 | B275: 2025 | C275: Electronics Fund | D275: 0 | E275: 319.18 | F275: 469.18
A276: 9 | B276: 2025 | C276: Electronics Fund | D276: 0 | E276: 469.18 | F276: 619.18
A277: 10 | B277: 2025 | C277: Electronics Fund | D277: 0 | E277: 619.18 | F277: 769.18
A278: 11 | B278: 2025 | C278: Electronics Fund | D278: 0 | E278: 769.18 | F278: 919.18
... A303: 12 | B303: 2025 | C303: Entertainment | D303: 0 | E303: 57.43 | F303: 207.43
A304: 1 | B304: 2024 | C304: Expense Type | D304: 0
A305: 1 | B305: 2024 | C305: Fast Food | D305: 0 | E305: 46 | F305: 46
A306: 2 | B306: 2024 | C306: Fast Food | D306: -79.07 | E306: 46 | F306: 16.93
A307: 3 | B307: 2024 | C307: Fast Food | D307: -54.64 | E307: 16.93 | F307: 12.29
A308: 4 | B308: 2024 | C308: Fast Food | D308: -112.15 | E308: 12.29 | F308: -49.86
A309: 5 | B309: 2024 | C309: Fast Food | D309: -25.66 | E309: -49.86 | F309: -25.52
A310: 6 | B310: 2024 | C310: Fast Food | D310: -38.09 | E310: -25.52 | F310: -13.61
A311: 7 | B311: 2024 | C311: Fast Food | D311: -43.9 | E311: -13.61 | F311: -7.51
A312: 8 | B312: 2024 | C312: Fast Food | D312: -26.67 | E312: -7.51 | F312: 15.82
A313: 9 | B313: 2024 | C313: Fast Food | D313: -81.65 | E313: 15.82 | F313: -15.83
A314: 10 | B314: 2024 | C314: Fast Food | D314: -59.37 | E314: -15.83 | F314: -25.2
A315: 11 | B315: 2024 | C315: Fast Food | D315: -2.09 | E315: -25.2 | F315: 22.71
A316: 12 | B316: 2024 | C316: Fast Food | D316: -41.42 | E316: 22.71 | F316: 31.29
... A866: 12 | B866: 2025 | C866: Subscriptions | D866: 0 | E866: 301.67 | F866: 310.33
A867: 1 | B867: 2024 | C867: Total | D867: 0
A868: 1 | B868: 2024 | C868: Vacation Fund | D868: 0 | E868: 1769.34 | F868: 1769.34
A869: 2 | B869: 2024 | C869: Vacation Fund | D869: -514.22 | E869: 1769.34 | F869: 1255.13
A870: 3 | B870: 2024 | C870: Vacation Fund | D870: -1515.37 | E870: 1255.13 | F870: -60.24
A871: 4 | B871: 2024 | C871: Vacation Fund | D871: 0 | E871: -60.24 | F871: 139.76
A872: 5 | B872: 2024 | C872: Vacation Fund | D872: 0 | E872: 139.76 | F872: 339.76
A873: 6 | B873: 2024 | C873: Vacation Fund | D873: 0 | E873: 339.76 | F873: 539.76
A874: 7 | B874: 2024 | C874: Vacation Fund | D874: -332.12 | E874: 539.76 | F874: 407.64
A875: 8 | B875: 2024 | C875: Vacation Fund | D875: 0 | E875: 407.64 | F875: 607.64
A876: 9 | B876: 2024 | C876: Vacation Fund | D876: 0 | E876: 607.64 | F876: 807.64
A877: 10 | B877: 2024 | C877: Vacation Fund | D877: -1077.73 | E877: 807.64 | F877: -70.09
A878: 11 | B878: 2024 | C878: Vacation Fund | D878: 0 | E878: -70.09 | F878: 129.91
A879: 12 | B879: 2024 | C879: Vacation Fund | D879: 336.07 | E879: 129.91 | F879: 665.98
... A939: 12 | B939: 2025 | C939: Weekend Trips | D939: 0 | E939: -175.83 | F939: -35.83

Sheet ChangeHistory
A1: Expense | B1: Month Start | C1: Year Start | D1: StartDate | E1: Month End | F1: Year End | G1: EndDate | H1: Amount
A2: Alcohol | B2: 2 | C2: 2024 | D2: =DATE(BudgetHistory[[#This Row],[Year Start]],BudgetHistory[[#This Row],[Month Start]],1) -> 45323 | E2: 2 | F2: 2024 | G2: =EOMONTH(DATE(BudgetHistory[[#This Row],[Year End]],BudgetHistory[[#This Row],[Month End]],1),0) -> 45351 | H2: 0.01
A3: Auto Insurance | B3: 3 | C3: 2024 | D3: =DATE(BudgetHistory[[#This Row],[Year Start]],BudgetHistory[[#This Row],[Month Start]],1) -> 45352 | E3: 3 | F3: 2025 | G3: =EOMONTH(DATE(BudgetHistory[[#This Row],[Year End]],BudgetHistory[[#This Row],[Month End]],1),0) -> 45747 | H3: 226
A4: Auto Insurance | B4: 2 | C4: 2024 | D4: =DATE(BudgetHistory[[#This Row],[Year Start]],BudgetHistory[[#This Row],[Month Start]],1) -> 45323 | E4: 2 | F4: 2024 | G4: =EOMONTH(DATE(BudgetHistory[[#This Row],[Year End]],BudgetHistory[[#This Row],[Month End]],1),0) -> 45351 | H4: 204
A5: Bar Night | B5: 2 | C5: 2024 | D5: =DATE(BudgetHistory[[#This Row],[Year Start]],BudgetHistory[[#This Row],[Month Start]],1) -> 45323 | E5: 2 | F5: 2024 | G5: =EOMONTH(DATE(BudgetHistory[[#This Row],[Year End]],BudgetHistory[[#This Row],[Month End]],1),0) -> 45351 | H5: 0.01
A6: Business Line | B6: 11 | C6: 2024 | D6: =DATE(BudgetHistory[[#This Row],[Year Start]],BudgetHistory[[#This Row],[Month Start]],1) -> 45597 | E6: 11 | F6: 2024 | G6: =EOMONTH(DATE(BudgetHistory[[#This Row],[Year End]],BudgetHistory[[#This Row],[Month End]],1),0) -> 45626 | H6: 0.001
A7: Car Maintenance | B7: 3 | C7: 2024 | D7: =DATE(BudgetHistory[[#This Row],[Year Start]],BudgetHistory[[#This Row],[Month Start]],1) -> 45352 | E7: 6 | F7: 2025 | G7: =EOMONTH(DATE(BudgetHistory[[#This Row],[Year End]],BudgetHistory[[#This Row],[Month End]],1),0) -> 45838 | H7: 100
A8: Car Maintenance | B8: 2 | C8: 2024 | D8: =DATE(BudgetHistory[[#This Row],[Year Start]],BudgetHistory[[#This Row],[Month Start]],1) -> 45323 | E8: 2 | F8: 2024 | G8: =EOMONTH(DATE(BudgetHistory[[#This Row],[Year End]],BudgetHistory[[#This Row],[Month End]],1),0) -> 45351 | H8: 0.01
A9: Cat Fund | B9: 2 | C9: 2024 | D9: =DATE(BudgetHistory[[#This Row],[Year Start]],BudgetHistory[[#This Row],[Month Start]],1) -> 45323 | E9: 4 | F9: 2024 | G9: =EOMONTH(DATE(BudgetHistory[[#This Row],[Year End]],BudgetHistory[[#This Row],[Month End]],1),0) -> 45412 | H9: 100
A10: Clothes | B10: 2 | C10: 2024 | D10: =DATE(BudgetHistory[[#This Row],[Year Start]],BudgetHistory[[#This Row],[Month Start]],1) -> 45323 | E10: 2 | F10: 2024 | G10: =EOMONTH(DATE(BudgetHistory[[#This Row],[Year End]],BudgetHistory[[#This Row],[Month End]],1),0) -> 45351 | H10: 0.01
A11: Credit Line | B11: 8 | C11: 2024 | D11: =DATE(BudgetHistory[[#This Row],[Year Start]],BudgetHistory[[#This Row],[Month Start]],1) -> 45505 | E11: 9 | F11: 2024 | G11: =EOMONTH(DATE(BudgetHistory[[#This Row],[Year End]],BudgetHistory[[#This Row],[Month End]],1),0) -> 45565 | H11: 150
A12: Health | B12: 2 | C12: 2024 | D12: =DATE(BudgetHistory[[#This Row],[Year Start]],BudgetHistory[[#This Row],[Month Start]],1) -> 45323 | E12: 5 | F12: 2025 | G12: =EOMONTH(DATE(BudgetHistory[[#This Row],[Year End]],BudgetHistory[[#This Row],[Month End]],1),0) -> 45808 | H12: 150
A13: Credit Line | B13: 2 | C13: 2024 | D13: =DATE(BudgetHistory[[#This Row],[Year Start]],BudgetHistory[[#This Row],[Month Start]],1) -> 45323 | E13: 7 | F13: 2024 | G13: =EOMONTH(DATE(BudgetHistory[[#This Row],[Year End]],BudgetHistory[[#This Row],[Month End]],1),0) -> 45504 | H13: 500
... A41: Weekend Trips | B41: 2 | C41: 2024 | D41: =DATE(BudgetHistory[[#This Row],[Year Start]],BudgetHistory[[#This Row],[Month Start]],1) -> 45323 | E41: 2 | F41: 2024 | G41: =EOMONTH(DATE(BudgetHistory[[#This Row],[Year End]],BudgetHistory[[#This Row],[Month End]],1),0) -> 45351 | H41: 0.01
D46: 294

Sheet CategoryRules
A1: Match 1 | B1: Match 2 | C1: Amount | D1: Expense Type
A2: ALAN & MICHELLE'S NF N | D2: Grocery
A3: AMZN Mktp | D3: Shopping Fund
A4: AUTO INSURANCE | D4: Auto Insurance
A5: AUTOMATIC PAYMENT - THANK YOU | D5: Ignore
A6: B.Y TAKE OUT NORTH BAY ON | D6: Expense Type
A7: CDN TIRE STORE | D7: House Fund
A8: DEPOSIT INTEREST | D8: Misc Fees
A9: DOLLAR TREE | D9: Shopping Fund
A10: DOLLARAMA | D10: Shopping Fund
A11: DOMINOS PIZZA | D11: Fast Food
A12: EAGLES NEST GAS BAR NORTH BAY ON | D12: Car Fuel
A13: Email Trfs | D13: Expense Type
... A22: HYDRO BILL PMT | D22: Hydro
A23: INSURANCE | B23: CANADALIFE | D23: Private Insurances
A24: INTEREST PAYMENT | D24: Misc Fees
A25: INVESTMENT | B25: IG FIN SER SFGI | D25: RRSP
A26: JOCKO POINT GEN7 LP NORTH BAY ON | D26: Car Fuel
A27: JOHNNY GS RESTAURANT WINNIPEG MB | D27: Entertainment
A28: KOODO MOBILE | D28: Phone Bills
A29: LCBO | D29: Alcohol
A30: LIFE INSURANCE | B30: CANLIFE-ING | D30: Private Insurances
A31: LOAN INTEREST | D31: Misc Fees
A32: Loan Pmt | D32: Credit Line
A33: LOANPROTECTOR INSURANCE PREMIUM | D33: Misc Fees
A34: MAGNOTTA WINERY ESTATE SUDBURY ON | D34: Alcohol
A35: MCDONALD | D35: Fast Food
A36: MISC PAYMENT | B36: CITY OF NORTH B | D36: Land Taxes
A37: MISC PAYMENT | B37: Fit4less | D37: Gym
A38: MISC PAYMENT | B38: MORTGAGE PAYMEN | D38: Mortgage
A39: MISC PAYMENT | B39: RBC CREDIT CARD | D39: Ignore
A40: MONTHLY FEE | D40: Misc Fees
A41: MR. SUB | D41: Fast Food
A42: MUTUAL FUNDS | B42: SPECIAL DEPOSIT | D42: RRSP
A43: NORTH BAY REGIONAL HEALTH705-495-8125 ON | D43: Lottery
A44: OD INTEREST | D44: Misc Fees
A45: OD PROTECTION FEE | D45: Misc Fees
A46: PARKN FLY | D46: Vacation Fund
A47: Payment | D47: Sewer/Water
A48: PAYMENT - THANK YOU / PAIEMENT - MERCI | D48: Ignore
A49: PAYROLL DEPOSIT | B49: ClaimSecure Inc | D49: Ignore
A50: PAYROLL DEPOSIT | B50: Thinking Big In | D50: Ignore
A51: PETRO CANADA | D51: Car Fuel
A52: PROPERTY INSURANCE | B52: ALLSTATE INS. | D52: Home Insurance
A53: REXALL PHARMACY | D53: Health
A54: SAFEWAY | D54: Grocery
A55: SERVICE FEE | D55: Misc Fees
A56: SOBEYS | D56: Grocery
A57: SPORTSCUT NORTH BAY ON | D57: Personal Hygiene
A58: SQ *GOOD GLAZE DOUGHNUTS | D58: Fast Food
A59: THE HOME DEPOT | D59: House Fund
A60: THE MASSAGE THERAPY CLININORTH BAY ON | D60: Health
A61: TIM HORTONS | D61: Fast Food
A62: Transfer | D62: Expense Type
A63: UTILITY BILL PMT | B63: Enbridge Gas | D63: Heat/Gas
A64: VIRGIN PLUS VERDUN QC | D64: Internet Bill
A65: Vistaprint | D65: Gifts
A66: WAL-MART SUPERCENTER | D66: Shopping Fund
A67: WWW PMT | D67: Expense Type
A68: WWW TFR | D68: Expense Type
A69: WWW TRF | D69: Expense Type
A70: LYNX | D70: Entertainment
A71: FESTIVAL | D71: Entertainment
A72: WDW | D72: Vacation Fund
A73: TOPPER'S PIZZA | D73: Fast Food
A74: PETS | D74: Cat Fund
A75: SKIPTHEDISHES | D75: Fast Food
... A77: LUCKYS RESTAURANT | D77: Date Night
A78: RED ROOF INN 0680 WYTHEVILLE VA | B78: 86.00 USD @ 1.387300000000 | D78: Expense Type
A79: CANADIAN TIRE GAS BAR | D79: Car Fuel
A80: STARBUCKS 70917 GROVE CITY PA | B80: 14.31 USD @ 1.394800000000 | D80: Expense Type
A81: GO MART #92 GASSAWAY WV | B81: 32.58 USD @ 1.384200000000 | D81: Expense Type
A82: GO MART #96 WYTHEVILLE VA | B82: 10.80 USD @ 1.387900000000 | D82: Expense Type
A83: HARDEES 2906 WYTHEVILLE VA | B83: 26.02 USD @ 1.387300000000 | D83: Expense Type
A84: RED ROOF INN 0680 708-9410062 VA | B84: 50.00 USD @ 1.311600000000 | D84: Expense Type
A85: QT 1176 INSIDE CAYCE SC | B85: 5.19 USD @ 1.387200000000 | D85: Expense Type
A86: QT 1176 OUTSIDE CAYCE SC | B86: 32.64 USD @ 1.384100000000 | D86: Expense Type
A87: ORMOND GARAGE ORMOND BEACH FL | B87: 50.06 USD @ 1.384300000000 | D87: Expense Type
A88: ABC FINE WINE/SPIRITS 210TALLAHA | B88: 122.59 USD @ 1.384300000000 | D88: Expense Type
A89: JIMMY HULAS - ORMOND ORMOND BEAC | B89: 24.18 USD @ 1.384600000000 | D89: Expense Type
A90: WALGREENS 0774 ORMOND BEACH FL | D90: Expense Type
A91: PUBLIX #1755 ORMOND BEACH FL | B91: 43.57 USD @ 1.419500000000 | D91: Expense Type
A92: SQ *OCEAN CLUB Ormond Beach FL | B92: 6.38 USD @ 1.421600000000 | D92: Expense Type
A93: TST* LULUS OCEANSIDE GRILOrmond | B93: 107.84 USD @ 1.418500000000 | D93: Expense Type
A94: Cracker Barrel 800-3339963 TN | B94: 21.17 USD @ 1.422700000000 | D94: Expense Type
A95: FLYING J 713 LATTA SC | B95: 32.39 USD @ 1.422900000000 | D95: Expense Type
A96: SUPER 8 MOTELS GARYSBURG NC | B96: 91.33 USD @ 1.422800000000 | D96: Expense Type
A97: RACETRAC661 00006619 ORMOND BEAC | B97: 36.13 USD @ 1.424000000000 | D97: Expense Type
A98: CHICK-FIL-A #01948 JACKSONVILLE | B98: 20.63 USD @ 1.418300000000 | D98: Expense Type
A99: ROCAR MOBILITY LLC HTTPSROCARMOB | B99: 15.89 USD @ 1.422900000000 | D99: Expense Type
A100: ROCAR MOBILITY LLC HTTPSROCARMOB | B100: 16.30 USD @ 1.422600000000 | D100: Expense Type
A101: Subway | B101: 21.76 USD @ 1.422700000000 | D101: Fast Food
A102: WENDY'S 191-23 WILLIAMSPORT PA | B102: 16.94 USD @ 1.423800000000 | D102: Expense Type
... A109: PREMIER WINES & SPIRITS AMHERST | B109: 219.56 USD @ 1.424300000000 | D109: Expense Type
A110: SUBWAY (HYBRID) KING CITY ON | D110: Expense Type
A111: NF BRIDGE COMMISSION R NIAGARA FALLSON | D111: Expense Type
A112: ONROUTE KING CITY ON | D112: Expense Type
A113: EXXON DANSVILLE VILLAGE MDANSVIL | B113: 32.89 USD @ 1.424100000000 | D113: Expense Type
A114: ONROUTE KING CITY 400 #11KING CITY ON | D114: Expense Type
A115: ANCHOR BAR RESTAURANT BUFFALO NY | B115: 48.92 USD @ 1.424100000000 | D115: Expense Type
...

Sheet Accounts
A1: Accounts
A2: Number | B2: Name | C2: Cushion | D2: Expected | E2: Total | F2: Actual | G2: Surplus | I2: Mel Load Amount | K2: 5000
A3: 00912-5106893 | B3: Steven Personal Chequing | C3: 0 | D3: N/A | E3: =Accounts[[#This Row],[Cushion]]+Accounts[[#This Row],[Expected]] -> #VALUE! | G3: =Accounts[[#This Row],[Actual]]-Accounts[[#This Row],[Expected]] -> #VALUE! | J3: Savings Self-Loan amount | K3: 6125
A4: 00912-5106901 | B4: Steven Personal Savings | C4: 0 | D4: N/A | E4: =Accounts[[#This Row],[Cushion]]+Accounts[[#This Row],[Expected]] -> #VALUE! | G4: =Accounts[[#This Row],[Actual]]-Accounts[[#This Row],[Expected]] -> #VALUE! | J4: Temp accrual amount | K4: =1900+2000+341.05+355 -> 4596.05
A5: 04982-5186838 | B5: Shared Chequings | C5: ? | D5: =SUM(Budget!G3:G26)+Accounts[[#This Row],[Cushion]] -> #VALUE! | E5: =Accounts[[#This Row],[Cushion]]+Accounts[[#This Row],[Expected]] -> #VALUE! | F5: ? | G5: =Accounts[[#This Row],[Actual]]-Accounts[[#This Row],[Expected]] -> #VALUE!
A6: 04982-5059290 | B6: Shared Savings | C6: 0 | D6: =SUM(Budget!S3:S13) -> 3357.23 | E6: =Accounts[[#This Row],[Expected]]+Accounts[[#This Row],[Cushion]]+K3+K4 -> 14078.28 | F6: 2068.12 | G6: =Accounts[[#This Row],[Cushion]]+Accounts[[#This Row],[Expected]] -> 3357.23
A7: 4510142620407531 | B7: Steven Visa | C7: 0 | D7: N/A | E7: =Accounts[[#This Row],[Cushion]]+Accounts[[#This Row],[Expected]] -> #VALUE! | G7: =Accounts[[#This Row],[Actual]]-Accounts[[#This Row],[Expected]] -> #VALUE!
A8: 4510158011413292 | B8: Shared Visa | C8: 0 | D8: N/A | E8: =Accounts[[#This Row],[Cushion]]+Accounts[[#This Row],[Expected]] -> #VALUE! | G8: =Accounts[[#This Row],[Actual]]-Accounts[[#This Row],[Expected]] -> #VALUE!
A9: 04982-35098277001 | B9: Credit Line | C9: 0 | D9: N/A | E9: =Accounts[[#This Row],[Cushion]]+Accounts[[#This Row],[Expected]] -> #VALUE! | G9: =Accounts[[#This Row],[Actual]]-Accounts[[#This Row],[Expected]] -> #VALUE!
